Workbook

Sheet PRODUCTOS
A1: ID | B1: CODIGO | C1: CATEGORIA | D1: SUBCATEGORIA | E1: MARCA | F1: PRODUCTO | G1: FRAGANCIA | H1: PRESENTACION | I1: NOMBRE FOTO | J1: COSTO | K1: % MARGEN | L1: PRECIO VENTA | M1: STOCK | N1: STOCK MINIMO | O1: ESTADO | P1: DESTACADO | Q1: SLUG | R1: DESCRIPCION | S1: CARACTERISTICAS | T1: EMPAQUE/PRODUCTO | U1: VIÁTICO PRORRATEADO | V1: SUBSIDIO ENVÍO PRORR. | W1: COMISIÓN COBRO | X1: MARGEN BRUTO OBJ. | Y1: PRECIO VENTA AJUSTADO | Z1: GANANCIA BRUTA EST. | AA1: MARGEN BRUTO EST. | AB1: GRUPO | AC1: VARIANTE
A2: 001 | B2: CLO001 | C2: 🚽 Baño | D2: Lavandina | E2: bethel | F2: Lavandina al 4% | G2: sin frangancia | H2: 5 litros | I2: CLO001.jpg | J2: 3300 | K2: 0.4 | L2: =IF(J2="","",J2*(1+K2)) -> 4620 | M2: Activo | O2: Activo | P2: NO | Q2: CLO001 | R2: Lavandina al 4%. Presentación: 5 litros. | S2: Lavandina. Elimina suciedad y gérmenes en inodoros, azulejos y superficies del baño, dejando un aroma agradable. | T2: ='SUPUESTOS PRECIOS'!$B$9 -> 0 | U2: ='SUPUESTOS PRECIOS'!$B$5/'SUPUESTOS PRECIOS'!$B$4 -> 1000 | V2: =('SUPUESTOS PRECIOS'!$B$6-'SUPUESTOS PRECIOS'!$B$7)/'SUPUESTOS PRECIOS'!$B$4 -> 377.5 | W2: ='SUPUESTOS PRECIOS'!$B$8 -> 0.00968 | X2: ='SUPUESTOS PRECIOS'!$B$2 -> 0.4 | Y2: =IF(OR($B2="",$J2=""),"",ROUND(($J2+$T2+$U2+$V2)/(1-$W2-$X2),-1)) -> 7920 | Z2: =IF($Y2="","",$Y2-$J2-$T2-$U2-$V2-($Y2*$W2)) -> 3165.8344 | AA2: =IF($Y2="","",$Z2/$Y2) -> 0.39972657
A3: 002 | B3: DET001 | C3: 🍽️ Cocina | D3: Detergente concentrado | E3: bethel | F3: Detergente 30% | G3: sin frangancia | H3: 5 litros | I3: DET001.jpg | J3: 9000 | K3: 0.3 | L3: =IF(J3="","",J3*(1+K3)) -> 11700 | M3: Activo | O3: Activo | P3: NO | Q3: DET001 | R3: Detergente 30%. Presentación: 5 litros. | S3: Detergente concentrado. Ideal para desengrasar y limpiar utensilios, vajilla y superficies de cocina de forma rápida y efectiva. | T3: ='SUPUESTOS PRECIOS'!$B$9 -> 0 | U3: ='SUPUESTOS PRECIOS'!$B$5/'SUPUESTOS PRECIOS'!$B$4 -> 1000 | V3: =('SUPUESTOS PRECIOS'!$B$6-'SUPUESTOS PRECIOS'!$B$7)/'SUPUESTOS PRECIOS'!$B$4 -> 377.5 | W3: ='SUPUESTOS PRECIOS'!$B$8 -> 0.00968 | X3: ='SUPUESTOS PRECIOS'!$B$2 -> 0.4 | Y3: =IF(OR($B3="",$J3=""),"",ROUND(($J3+$T3+$U3+$V3)/(1-$W3-$X3),-1)) -> 17580 | Z3: =IF($Y3="","",$Y3-$J3-$T3-$U3-$V3-($Y3*$W3)) -> 7032.3256 | AA3: =IF($Y3="","",$Z3/$Y3) -> 0.40001852
A4: 003 | B4: LVA001 | C4: 🍽️ Cocina | D4: Detergente listo para usar | E4: bethel | F4: Detergente Magistral listo para usar | G4: sin frangancia | H4: 5 litros | I4: LVA001.jpg | J4: 2750 | K4: 0.3 | L4: =IF(J4="","",J4*(1+K4)) -> 3575 | M4: Activo | O4: Activo | P4: NO | Q4: LVA001 | R4: Detergente Magistral listo para usar. Presentación: 5 litros. | S4: Detergente listo para usar. Ideal para desengrasar y limpiar utensilios, vajilla y superficies de cocina de forma rápida y efectiva. | T4: ='SUPUESTOS PRECIOS'!$B$9 -> 0 | U4: ='SUPUESTOS PRECIOS'!$B$5/'SUPUESTOS PRECIOS'!$B$4 -> 1000 | V4: =('SUPUESTOS PRECIOS'!$B$6-'SUPUESTOS PRECIOS'!$B$7)/'SUPUESTOS PRECIOS'!$B$4 -> 377.5 | W4: ='SUPUESTOS PRECIOS'!$B$8 -> 0.00968 | X4: ='SUPUESTOS PRECIOS'!$B$2 -> 0.4 | Y4: =IF(OR($B4="",$J4=""),"",ROUND(($J4+$T4+$U4+$V4)/(1-$W4-$X4),-1)) -> 6990 | Z4: =IF($Y4="","",$Y4-$J4-$T4-$U4-$V4-($Y4*$W4)) -> 2794.8368 | AA4: =IF($Y4="","",$Z4/$Y4) -> 0.39983359
A5: 004 | B5: LVA002 | C5: 🍽️ Cocina | D5: Lava-vajillas concentrado | E5: bethel | F5: Lava-Vajillas Concentrado | H5: 5 litros | I5: LVA002.jpg | J5: 3250 | K5: 0.3 | L5: =IF(J5="","",J5*(1+K5)) -> 4225 | M5: Activo | O5: Activo | P5: NO | Q5: LVA002 | R5: Lava-Vajillas Concentrado. Presentación: 5 litros. | S5: Lava-vajillas concentrado. Ideal para desengrasar y limpiar utensilios, vajilla y superficies de cocina de forma rápida y efectiva. | T5: ='SUPUESTOS PRECIOS'!$B$9 -> 0 | U5: ='SUPUESTOS PRECIOS'!$B$5/'SUPUESTOS PRECIOS'!$B$4 -> 1000 | V5: =('SUPUESTOS PRECIOS'!$B$6-'SUPUESTOS PRECIOS'!$B$7)/'SUPUESTOS PRECIOS'!$B$4 -> 377.5 | W5: ='SUPUESTOS PRECIOS'!$B$8 -> 0.00968 | X5: ='SUPUESTOS PRECIOS'!$B$2 -> 0.4 | Y5: =IF(OR($B5="",$J5=""),"",ROUND(($J5+$T5+$U5+$V5)/(1-$W5-$X5),-1)) -> 7840 | Z5: =IF($Y5="","",$Y5-$J5-$T5-$U5-$V5-($Y5*$W5)) -> 3136.6088 | AA5: =IF($Y5="","",$Z5/$Y5) -> 0.40007765
A6: 005 | B6: SUA001 | C6: 👕 Ropa y lavado | D6: Suavizante | E6: bethel | F6: Suavizante Blanco por 5 litros | G6: color blanco premium | H6: 5 litros | I6: SUA001.jpg | J6: 5000 | K6: 0.3 | L6: =IF(J6="","",J6*(1+K6)) -> 6500 | M6: Activo | O6: Activo | P6: NO | Q6: SUA001 | R6: Suavizante Blanco por 5 litros. Presentación: 5 litros. Fragancia: color blanco premium. | S6: Suavizante. Cuida las fibras de la ropa, suaviza y deja un aroma agradable y duradero en cada lavado. | T6: ='SUPUESTOS PRECIOS'!$B$9 -> 0 | U6: ='SUPUESTOS PRECIOS'!$B$5/'SUPUESTOS PRECIOS'!$B$4 -> 1000 | V6: =('SUPUESTOS PRECIOS'!$B$6-'SUPUESTOS PRECIOS'!$B$7)/'SUPUESTOS PRECIOS'!$B$4 -> 377.5 | W6: ='SUPUESTOS PRECIOS'!$B$8 -> 0.00968 | X6: ='SUPUESTOS PRECIOS'!$B$2 -> 0.4 | Y6: =IF(OR($B6="",$J6=""),"",ROUND(($J6+$T6+$U6+$V6)/(1-$W6-$X6),-1)) -> 10800 | Z6: =IF($Y6="","",$Y6-$J6-$T6-$U6-$V6-($Y6*$W6)) -> 4317.956 | AA6: =IF($Y6="","",$Z6/$Y6) -> 0.39981074
A7: 006 | B7: SUA002 | C7: 👕 Ropa y lavado | D7: Tradicional | E7: bethel | F7: Suavizante listo para usar | G7: color celeste economico | H7: 5 litros | I7: SUA002.jpg | J7: 4000 | K7: 0.3 | L7: =IF(J7="","",J7*(1+K7)) -> 5200 | M7: Activo | O7: Activo | P7: NO | Q7: SUA002 | R7: Suavizante listo para usar. Presentación: 5 litros. Fragancia: color celeste economico. | S7: Tradicional. Cuida las fibras de la ropa, suaviza y deja un aroma agradable y duradero en cada lavado. | T7: ='SUPUESTOS PRECIOS'!$B$9 -> 0 | U7: ='SUPUESTOS PRECIOS'!$B$5/'SUPUESTOS PRECIOS'!$B$4 -> 1000 | V7: =('SUPUESTOS PRECIOS'!$B$6-'SUPUESTOS PRECIOS'!$B$7)/'SUPUESTOS PRECIOS'!$B$4 -> 377.5 | W7: ='SUPUESTOS PRECIOS'!$B$8 -> 0.00968 | X7: ='SUPUESTOS PRECIOS'!$B$2 -> 0.4 | Y7: =IF(OR($B7="",$J7=""),"",ROUND(($J7+$T7+$U7+$V7)/(1-$W7-$X7),-1)) -> 9110 | Z7: =IF($Y7="","",$Y7-$J7-$T7-$U7-$V7-($Y7*$W7)) -> 3644.3152 | AA7: =IF($Y7="","",$Z7/$Y7) -> 0.4000346
A8: 007 | B8: JBP001 | C8: 👕 Ropa y lavado | D8: Tradicional | E8: granby | F8: Jabon en polvo | H8: 20 kg | I8: JBP001.jpg | J8: 20000 | K8: 0.3 | L8: =IF(J8="","",J8*(1+K8)) -> 26000 | M8: Activo | O8: Activo | P8: NO | Q8: JBP001 | R8: Jabon en polvo. Presentación: 20 kg. Marca granby. | S8: Tradicional. Cuida las fibras de la ropa, suaviza y deja un aroma agradable y duradero en cada lavado. | T8: ='SUPUESTOS PRECIOS'!$B$9 -> 0 | U8: ='SUPUESTOS PRECIOS'!$B$5/'SUPUESTOS PRECIOS'!$B$4 -> 1000 | V8: =('SUPUESTOS PRECIOS'!$B$6-'SUPUESTOS PRECIOS'!$B$7)/'SUPUESTOS PRECIOS'!$B$4 -> 377.5 | W8: ='SUPUESTOS PRECIOS'!$B$8 -> 0.00968 | X8: ='SUPUESTOS PRECIOS'!$B$2 -> 0.4 | Y8: =IF(OR($B8="",$J8=""),"",ROUND(($J8+$T8+$U8+$V8)/(1-$W8-$X8),-1)) -> 36210 | Z8: =IF($Y8="","",$Y8-$J8-$T8-$U8-$V8-($Y8*$W8)) -> 14481.987 | AA8: =IF($Y8="","",$Z8/$Y8) -> 0.39994441
A9: 008 | B9: PFA001 | C9: 🌸 Aromas y fragancias | D9: Perfumes para ropa | E9: bethel | F9: Perfume aromatico de base en agua | G9: 1056, algodón, arpege, bazzu, bebe, c.h.242 , coco, uva, flores blancas, caricias, confy, limon, melon, premium, sandia/frambuesa , softy, ultra, comiglio, vainilla, vivex, flores silvestres, chocolate | H9: 1 litros | I9: PFA001.jpg | J9: 2200 | K9: 0.3 | L9: =IF(J9="","",J9*(1+K9)) -> 2860 | M9: Activo | O9: Activo | P9: NO | Q9: PFA001 | R9: Perfume aromatico de base en agua. Presentación: 1 litros. | S9: Perfumes para ropa. Perfuma ambientes y textiles con una fragancia agradable y duradera, ideal para dejar todo con olor a limpio. Disponible en múltiples fragancias a elección. | T9: ='SUPUESTOS PRECIOS'!$B$9 -> 0 | U9: ='SUPUESTOS PRECIOS'!$B$5/'SUPUESTOS PRECIOS'!$B$4 -> 1000 | V9: =('SUPUESTOS PRECIOS'!$B$6-'SUPUESTOS PRECIOS'!$B$7)/'SUPUESTOS PRECIOS'!$B$4 -> 377.5 | W9: ='SUPUESTOS PRECIOS'!$B$8 -> 0.00968 | X9: ='SUPUESTOS PRECIOS'!$B$2 -> 0.4 | Y9: =IF(OR($B9="",$J9=""),"",ROUND(($J9+$T9+$U9+$V9)/(1-$W9-$X9),-1)) -> 6060 | Z9: =IF($Y9="","",$Y9-$J9-$T9-$U9-$V9-($Y9*$W9)) -> 2423.8392 | AA9: =IF($Y9="","",$Z9/$Y9) -> 0.39997347
A10: 009 | B10: PFA002 | C10: 🌸 Aromas y fragancias | D10: Perfumes para ropa | E10: bethel | F10: Perfume aromatico de base en alcohol | G10: 1056, algodón, arpege, bazzu, bebe, c.h.242 , coco, uva, flores blancas, caricias, confy, limon, melon, premium, sandia/frambuesa , softy, ultra, comiglio, vainilla, vivex, flores silvestres, chocolate | H10: 5 litros | I10: PFA002.jpg | J10: 16000 | K10: 0.3 | L10: =IF(J10="","",J10*(1+K10)) -> 20800 | M10: Activo | O10: Activo | P10: NO | Q10: PFA002 | R10: Perfume aromatico de base en alcohol. Presentación: 5 litros. | S10: Perfumes para ropa. Perfuma ambientes y textiles con una fragancia agradable y duradera, ideal para dejar todo con olor a limpio. Disponible en múltiples fragancias a elección. | T10: ='SUPUESTOS PRECIOS'!$B$9 -> 0 | U10: ='SUPUESTOS PRECIOS'!$B$5/'SUPUESTOS PRECIOS'!$B$4 -> 1000 | V10: =('SUPUESTOS PRECIOS'!$B$6-'SUPUESTOS PRECIOS'!$B$7)/'SUPUESTOS PRECIOS'!$B$4 -> 377.5 | W10: ='SUPUESTOS PRECIOS'!$B$8 -> 0.00968 | X10: ='SUPUESTOS PRECIOS'!$B$2 -> 0.4 | Y10: =IF(OR($B10="",$J10=""),"",ROUND(($J10+$T10+$U10+$V10)/(1-$W10-$X10),-1)) -> 29440 | Z10: =IF($Y10="","",$Y10-$J10-$T10-$U10-$V10-($Y10*$W10)) -> 11777.521 | AA10: =IF($Y10="","",$Z10/$Y10) -> 0.40005166
A11: 010 | B11: DES001 | C11: 🦠 Desinfección y limpieza | D11: Desengrasantes | E11: bethel | F11: Desengrasante industrial | H11: 5 litros | I11: DES001.jpg | J11: 4600 | K11: 0.3 | L11: =IF(J11="","",J11*(1+K11)) -> 5980 | M11: Activo | O11: Activo | P11: NO | Q11: DES001 | R11: Desengrasante industrial. Presentación: 5 litros. | S11: Desengrasantes. Elimina bacterias y gérmenes, desinfectando a fondo superficies del hogar, comercios e industrias. | T11: ='SUPUESTOS PRECIOS'!$B$9 -> 0 | U11: ='SUPUESTOS PRECIOS'!$B$5/'SUPUESTOS PRECIOS'!$B$4 -> 1000 | V11: =('SUPUESTOS PRECIOS'!$B$6-'SUPUESTOS PRECIOS'!$B$7)/'SUPUESTOS PRECIOS'!$B$4 -> 377.5 | W11: ='SUPUESTOS PRECIOS'!$B$8 -> 0.00968 | X11: ='SUPUESTOS PRECIOS'!$B$2 -> 0.4 | Y11: =IF(OR($B11="",$J11=""),"",ROUND(($J11+$T11+$U11+$V11)/(1-$W11-$X11),-1)) -> 10130 | Z11: =IF($Y11="","",$Y11-$J11-$T11-$U11-$V11-($Y11*$W11)) -> 4054.4416 | AA11: =IF($Y11="","",$Z11/$Y11) -> 0.40024103
A12: 011 | B12: DES002 | C12: 🦠 Desinfección y limpieza | D12: Desengrasantes | E12: bethel | F12: Desengrasante lavamotor | H12: 5 litros | I12: DES002.jpg | J12: 5400 | K12: 0.3 | L12: =IF(J12="","",J12*(1+K12)) -> 7020 | M12: Activo | O12: Activo | P12: NO | Q12: DES002 | R12: Desengrasante lavamotor. Presentación: 5 litros. | S12: Desengrasantes. Elimina bacterias y gérmenes, desinfectando a fondo superficies del hogar, comercios e industrias. | T12: ='SUPUESTOS PRECIOS'!$B$9 -> 0 | U12: ='SUPUESTOS PRECIOS'!$B$5/'SUPUESTOS PRECIOS'!$B$4 -> 1000 | V12: =('SUPUESTOS PRECIOS'!$B$6-'SUPUESTOS PRECIOS'!$B$7)/'SUPUESTOS PRECIOS'!$B$4 -> 377.5 | W12: ='SUPUESTOS PRECIOS'!$B$8 -> 0.00968 | X12: ='SUPUESTOS PRECIOS'!$B$2 -> 0.4 | Y12: =IF(OR($B12="",$J12=""),"",ROUND(($J12+$T12+$U12+$V12)/(1-$W12-$X12),-1)) -> 11480 | Z12: =IF($Y12="","",$Y12-$J12-$T12-$U12-$V12-($Y12*$W12)) -> 4591.3736 | AA12: =IF($Y12="","",$Z12/$Y12) -> 0.39994544
A13: 012 | B13: DES003 | C13: 🦠 Desinfección y limpieza | D13: Desengrasantes | E13: bethel | F13: Desengrasante multi usos | H13: 5 litros | I13: DES003.jpg | J13: 5400 | K13: 0.3 | L13: =IF(J13="","",J13*(1+K13)) -> 7020 | M13: Activo | O13: Activo | P13: NO | Q13: DES003 | R13: Desengrasante multi usos. Presentación: 5 litros. | S13: Desengrasantes. Elimina bacterias y gérmenes, desinfectando a fondo superficies del hogar, comercios e industrias. | T13: ='SUPUESTOS PRECIOS'!$B$9 -> 0 | U13: ='SUPUESTOS PRECIOS'!$B$5/'SUPUESTOS PRECIOS'!$B$4 -> 1000 | V13: =('SUPUESTOS PRECIOS'!$B$6-'SUPUESTOS PRECIOS'!$B$7)/'SUPUESTOS PRECIOS'!$B$4 -> 377.5 | W13: ='SUPUESTOS PRECIOS'!$B$8 -> 0.00968 | X13: ='SUPUESTOS PRECIOS'!$B$2 -> 0.4 | Y13: =IF(OR($B13="",$J13=""),"",ROUND(($J13+$T13+$U13+$V13)/(1-$W13-$X13),-1)) -> 11480 | Z13: =IF($Y13="","",$Y13-$J13-$T13-$U13-$V13-($Y13*$W13)) -> 4591.3736 | AA13: =IF($Y13="","",$Z13/$Y13) -> 0.39994544
A14: 013 | B14: DES004 | C14: 🦠 Desinfección y limpieza | D14: Desengrasantes | E14: bethel | F14: Desengrasante quima manchas | H14: 5 litros | I14: DES004.jpg | J14: 5400 | K14: 0.3 | L14: =IF(J14="","",J14*(1+K14)) -> 7020 | M14: Activo | O14: Activo | P14: NO | Q14: DES004 | R14: Desengrasante quima manchas. Presentación: 5 litros. | S14: Desengrasantes. Elimina bacterias y gérmenes, desinfectando a fondo superficies del hogar, comercios e industrias. | T14: ='SUPUESTOS PRECIOS'!$B$9 -> 0 | U14: ='SUPUESTOS PRECIOS'!$B$5/'SUPUESTOS PRECIOS'!$B$4 -> 1000 | V14: =('SUPUESTOS PRECIOS'!$B$6-'SUPUESTOS PRECIOS'!$B$7)/'SUPUESTOS PRECIOS'!$B$4 -> 377.5 | W14: ='SUPUESTOS PRECIOS'!$B$8 -> 0.00968 | X14: ='SUPUESTOS PRECIOS'!$B$2 -> 0.4 | Y14: =IF(OR($B14="",$J14=""),"",ROUND(($J14+$T14+$U14+$V14)/(1-$W14-$X14),-1)) -> 11480 | Z14: =IF($Y14="","",$Y14-$J14-$T14-$U14-$V14-($Y14*$W14)) -> 4591.3736 | AA14: =IF($Y14="","",$Z14/$Y14) -> 0.39994544
A15: 014 | B15: DES005 | C15: 🦠 Desinfección y limpieza | D15: Desengrasantes | E15: bethel | F15: Desengrasante limpiador cremoso | H15: 5 litros | I15: DES005.jpg | J15: 7300 | K15: 0.3 | L15: =IF(J15="","",J15*(1+K15)) -> 9490 | M15: Activo | O15: Activo | P15: NO | Q15: DES005 | R15: Desengrasante limpiador cremoso. Presentación: 5 litros. | S15: Desengrasantes. Elimina bacterias y gérmenes, desinfectando a fondo superficies del hogar, comercios e industrias. | T15: ='SUPUESTOS PRECIOS'!$B$9 -> 0 | U15: ='SUPUESTOS PRECIOS'!$B$5/'SUPUESTOS PRECIOS'!$B$4 -> 1000 | V15: =('SUPUESTOS PRECIOS'!$B$6-'SUPUESTOS PRECIOS'!$B$7)/'SUPUESTOS PRECIOS'!$B$4 -> 377.5 | W15: ='SUPUESTOS PRECIOS'!$B$8 -> 0.00968 | X15: ='SUPUESTOS PRECIOS'!$B$2 -> 0.4 | Y15: =IF(OR($B15="",$J15=""),"",ROUND(($J15+$T15+$U15+$V15)/(1-$W15-$X15),-1)) -> 14700 | Z15: =IF($Y15="","",$Y15-$J15-$T15-$U15-$V15-($Y15*$W15)) -> 5880.204 | AA15: =IF($Y15="","",$Z15/$Y15) -> 0.40001388
A16: 015 | B16: RJR001 | C16: 🧰 Accesorios y equipamiento | D16: Rejillas y repasadores | E16: bethel | F16: Franela 40x50 | H16: 1 unidad | I16: RJR001.jpg | J16: 700 | K16: 0.3 | L16: =IF(J16="","",J16*(1+K16)) -> 910 | M16: Activo | O16: Activo | P16: NO | Q16: RJR001 | R16: Franela 40x50. Presentación: 1 unidad. | S16: Rejillas y repasadores. Accesorio resistente y práctico, pensado para facilitar las tareas de limpieza del hogar. | T16: ='SUPUESTOS PRECIOS'!$B$9 -> 0 | U16: ='SUPUESTOS PRECIOS'!$B$5/'SUPUESTOS PRECIOS'!$B$4 -> 1000 | V16: =('SUPUESTOS PRECIOS'!$B$6-'SUPUESTOS PRECIOS'!$B$7)/'SUPUESTOS PRECIOS'!$B$4 -> 377.5 | W16: ='SUPUESTOS PRECIOS'!$B$8 -> 0.00968 | X16: ='SUPUESTOS PRECIOS'!$B$2 -> 0.4 | Y16: =IF(OR($B16="",$J16=""),"",ROUND(($J16+$T16+$U16+$V16)/(1-$W16-$X16),-1)) -> 3520 | Z16: =IF($Y16="","",$Y16-$J16-$T16-$U16-$V16-($Y16*$W16)) -> 1408.4264 | AA16: =IF($Y16="","",$Z16/$Y16) -> 0.40012114
A17: 016 | B17: RJR002 | C17: 🧰 Accesorios y equipamiento | D17: Rejillas y repasadores | E17: bethel | F17: Rejilla de cocina | H17: 1 unidad | I17: RJR002.jpg | J17: 300 | K17: 0.3 | L17: =IF(J17="","",J17*(1+K17)) -> 390 | M17: Activo | O17: Activo | P17: NO | Q17: RJR002 | R17: Rejilla de cocina. Presentación: 1 unidad. | S17: Rejillas y repasadores. Accesorio resistente y práctico, pensado para facilitar las tareas de limpieza del hogar. | T17: ='SUPUESTOS PRECIOS'!$B$9 -> 0 | U17: ='SUPUESTOS PRECIOS'!$B$5/'SUPUESTOS PRECIOS'!$B$4 -> 1000 | V17: =('SUPUESTOS PRECIOS'!$B$6-'SUPUESTOS PRECIOS'!$B$7)/'SUPUESTOS PRECIOS'!$B$4 -> 377.5 | W17: ='SUPUESTOS PRECIOS'!$B$8 -> 0.00968 | X17: ='SUPUESTOS PRECIOS'!$B$2 -> 0.4 | Y17: =IF(OR($B17="",$J17=""),"",ROUND(($J17+$T17+$U17+$V17)/(1-$W17-$X17),-1)) -> 2840 | Z17: =IF($Y17="","",$Y17-$J17-$T17-$U17-$V17-($Y17*$W17)) -> 1135.0088 | AA17: =IF($Y17="","",$Z17/$Y17) -> 0.39965099
A18: 017 | B18: RJR003 | C18: 🧰 Accesorios y equipamiento | D18: Rejillas y repasadores | E18: bethel | F18: Rejilla tipo americana | H18: 1 unidad | I18: RJR003.jpg | J18: 500 | K18: 0.3 | L18: =IF(J18="","",J18*(1+K18)) -> 650 | M18: Activo | O18: Activo | P18: NO | Q18: RJR003 | R18: Rejilla tipo americana. Presentación: 1 unidad. | S18: Rejillas y repasadores. Accesorio resistente y práctico, pensado para facilitar las tareas de limpieza del hogar. | T18: ='SUPUESTOS PRECIOS'!$B$9 -> 0 | U18: ='SUPUESTOS PRECIOS'!$B$5/'SUPUESTOS PRECIOS'!$B$4 -> 1000 | V18: =('SUPUESTOS PRECIOS'!$B$6-'SUPUESTOS PRECIOS'!$B$7)/'SUPUESTOS PRECIOS'!$B$4 -> 377.5 | W18: ='SUPUESTOS PRECIOS'!$B$8 -> 0.00968 | X18: ='SUPUESTOS PRECIOS'!$B$2 -> 0.4 | Y18: =IF(OR($B18="",$J18=""),"",ROUND(($J18+$T18+$U18+$V18)/(1-$W18-$X18),-1)) -> 3180 | Z18: =IF($Y18="","",$Y18-$J18-$T18-$U18-$V18-($Y18*$W18)) -> 1271.7176 | AA18: =IF($Y18="","",$Z18/$Y18) -> 0.39991119
A19: 018 | B19: RJR004 | C19: 🧰 Accesorios y equipamiento | D19: Rejillas y repasadores | E19: bethel | F19: Rejilla de auto | H19: 1 unidad | I19: RJR004.jpg | J19: 500 | K19: 0.3 | L19: =IF(J19="","",J19*(1+K19)) -> 650 | M19: Activo | O19: Activo | P19: NO | Q19: RJR004 | R19: Rejilla de auto. Presentación: 1 unidad. | S19: Rejillas y repasadores. Accesorio resistente y práctico, pensado para facilitar las tareas de limpieza del hogar. | T19: ='SUPUESTOS PRECIOS'!$B$9 -> 0 | U19: ='SUPUESTOS PRECIOS'!$B$5/'SUPUESTOS PRECIOS'!$B$4 -> 1000 | V19: =('SUPUESTOS PRECIOS'!$B$6-'SUPUESTOS PRECIOS'!$B$7)/'SUPUESTOS PRECIOS'!$B$4 -> 377.5 | W19: ='SUPUESTOS PRECIOS'!$B$8 -> 0.00968 | X19: ='SUPUESTOS PRECIOS'!$B$2 -> 0.4 | Y19: =IF(OR($B19="",$J19=""),"",ROUND(($J19+$T19+$U19+$V19)/(1-$W19-$X19),-1)) -> 3180 | Z19: =IF($Y19="","",$Y19-$J19-$T19-$U19-$V19-($Y19*$W19)) -> 1271.7176 | AA19: =IF($Y19="","",$Z19/$Y19) -> 0.39991119 | AB19: RJR-AUTO | AC19: SIMPLE
A20: 019 | B20: RJR005 | C20: 🧰 Accesorios y equipamiento | D20: Rejillas y repasadores | E20: bethel | F20: Rejilla de pabilo | H20: 1 unidad | I20: RJR005.jpg | J20: 500 | K20: 0.3 | L20: =IF(J20="","",J20*(1+K20)) -> 650 | M20: Activo | O20: Activo | P20: NO | Q20: RJR005 | R20: Rejilla de pabilo. Presentación: 1 unidad. | S20: Rejillas y repasadores. Accesorio resistente y práctico, pensado para facilitar las tareas de limpieza del hogar. | T20: ='SUPUESTOS PRECIOS'!$B$9 -> 0 | U20: ='SUPUESTOS PRECIOS'!$B$5/'SUPUESTOS PRECIOS'!$B$4 -> 1000 | V20: =('SUPUESTOS PRECIOS'!$B$6-'SUPUESTOS PRECIOS'!$B$7)/'SUPUESTOS PRECIOS'!$B$4 -> 377.5 | W20: ='SUPUESTOS PRECIOS'!$B$8 -> 0.00968 | X20: ='SUPUESTOS PRECIOS'!$B$2 -> 0.4 | Y20: =IF(OR($B20="",$J20=""),"",ROUND(($J20+$T20+$U20+$V20)/(1-$W20-$X20),-1)) -> 3180 | Z20: =IF($Y20="","",$Y20-$J20-$T20-$U20-$V20-($Y20*$W20)) -> 1271.7176 | AA20: =IF($Y20="","",$Z20/$Y20) -> 0.39991119
A21: 020 | B21: RJR006 | C21: 🧰 Accesorios y equipamiento | D21: Rejillas y repasadores | E21: bethel | F21: Rejilla de auto | H21: 1 unidad | I21: RJR006.jpg | J21: 2050 | K21: 0.3 | L21: =IF(J21="","",J21*(1+K21)) -> 2665 | M21: Activo | O21: Activo | P21: NO | Q21: RJR006 | R21: Rejilla de auto. Presentación: 1 unidad. | S21: Rejillas y repasadores. Accesorio resistente y práctico, pensado para facilitar las tareas de limpieza del hogar. | T21: ='SUPUESTOS PRECIOS'!$B$9 -> 0 | U21: ='SUPUESTOS PRECIOS'!$B$5/'SUPUESTOS PRECIOS'!$B$4 -> 1000 | V21: =('SUPUESTOS PRECIOS'!$B$6-'SUPUESTOS PRECIOS'!$B$7)/'SUPUESTOS PRECIOS'!$B$4 -> 377.5 | W21: ='SUPUESTOS PRECIOS'!$B$8 -> 0.00968 | X21: ='SUPUESTOS PRECIOS'!$B$2 -> 0.4 | Y21: =IF(OR($B21="",$J21=""),"",ROUND(($J21+$T21+$U21+$V21)/(1-$W21-$X21),-1)) -> 5810 | Z21: =IF($Y21="","",$Y21-$J21-$T21-$U21-$V21-($Y21*$W21)) -> 2326.2592 | AA21: =IF($Y21="","",$Z21/$Y21) -> 0.40038885 | AB21: RJR-AUTO | AC21: DOBLE
A22: 021 | B22: RJR007 | C22: 🧰 Accesorios y equipamiento | D22: Rejillas y repasadores | E22: bethel | F22: Rejilla de auto | H22: 1 unidad | I22: RJR007.jpg | J22: 2050 | K22: 0.3 | L22: =IF(J22="","",J22*(1+K22)) -> 2665 | M22: Activo | O22: Activo | P22: NO | Q22: RJR007 | R22: Rejilla de auto. Presentación: 1 unidad. | S22: Rejillas y repasadores. Accesorio resistente y práctico, pensado para facilitar las tareas de limpieza del hogar. | T22: ='SUPUESTOS PRECIOS'!$B$9 -> 0 | U22: ='SUPUESTOS PRECIOS'!$B$5/'SUPUESTOS PRECIOS'!$B$4 -> 1000 | V22: =('SUPUESTOS PRECIOS'!$B$6-'SUPUESTOS PRECIOS'!$B$7)/'SUPUESTOS PRECIOS'!$B$4 -> 377.5 | W22: ='SUPUESTOS PRECIOS'!$B$8 -> 0.00968 | X22: ='SUPUESTOS PRECIOS'!$B$2 -> 0.4 | Y22: =IF(OR($B22="",$J22=""),"",ROUND(($J22+$T22+$U22+$V22)/(1-$W22-$X22),-1)) -> 5810 | Z22: =IF($Y22="","",$Y22-$J22-$T22-$U22-$V22-($Y22*$W22)) -> 2326.2592 | AA22: =IF($Y22="","",$Z22/$Y22) -> 0.40038885 | AB22: RJR-AUTO | AC22: TRIPLE
A23: 022 | B23: RJR008 | C23: 🧰 Accesorios y equipamiento | D23: Rejillas y repasadores | E23: bethel | F23: Rejilla cocina | H23: 1 unidad | I23: RJR008.jpg | J23: 750 | K23: 0.3 | L23: =IF(J23="","",J23*(1+K23)) -> 975 | M23: Activo | O23: Activo | P23: NO | Q23: RJR008 | R23: Rejilla cocina. Presentación: 1 unidad. | S23: Rejillas y repasadores. Accesorio resistente y práctico, pensado para facilitar las tareas de limpieza del hogar. | T23: ='SUPUESTOS PRECIOS'!$B$9 -> 0 | U23: ='SUPUESTOS PRECIOS'!$B$5/'SUPUESTOS PRECIOS'!$B$4 -> 1000 | V23: =('SUPUESTOS PRECIOS'!$B$6-'SUPUESTOS PRECIOS'!$B$7)/'SUPUESTOS PRECIOS'!$B$4 -> 377.5 | W23: ='SUPUESTOS PRECIOS'!$B$8 -> 0.00968 | X23: ='SUPUESTOS PRECIOS'!$B$2 -> 0.4 | Y23: =IF(OR($B23="",$J23=""),"",ROUND(($J23+$T23+$U23+$V23)/(1-$W23-$X23),-1)) -> 3600 | Z23: =IF($Y23="","",$Y23-$J23-$T23-$U23-$V23-($Y23*$W23)) -> 1437.652 | AA23: =IF($Y23="","",$Z23/$Y23) -> 0.39934778 | AB23: RJR-COCINA | AC23: TRIPLE
A24: 023 | B24: RJR009 | C24: 🧰 Accesorios y equipamiento | D24: Rejillas y repasadores | E24: Kide | F24: Rejilla cocina | H24: 1 unidad | I24: RJR009.jpg | J24: 650 | K24: 0.3 | L24: =IF(J24="","",J24*(1+K24)) -> 845 | M24: Activo | O24: Activo | P24: NO | Q24: RJR009 | R24: Rejilla cocina. Presentación: 1 unidad. Marca Kide. | S24: Rejillas y repasadores. Accesorio resistente y práctico, pensado para facilitar las tareas de limpieza del hogar. | T24: ='SUPUESTOS PRECIOS'!$B$9 -> 0 | U24: ='SUPUESTOS PRECIOS'!$B$5/'SUPUESTOS PRECIOS'!$B$4 -> 1000 | V24: =('SUPUESTOS PRECIOS'!$B$6-'SUPUESTOS PRECIOS'!$B$7)/'SUPUESTOS PRECIOS'!$B$4 -> 377.5 | W24: ='SUPUESTOS PRECIOS'!$B$8 -> 0.00968 | X24: ='SUPUESTOS PRECIOS'!$B$2 -> 0.4 | Y24: =IF(OR($B24="",$J24=""),"",ROUND(($J24+$T24+$U24+$V24)/(1-$W24-$X24),-1)) -> 3430 | Z24: =IF($Y24="","",$Y24-$J24-$T24-$U24-$V24-($Y24*$W24)) -> 1369.2976 | AA24: =IF($Y24="","",$Z24/$Y24) -> 0.39921213 | AB24: RJR-COCINA | AC24: DOBLE
A25: 024 | B25: RJR010 | C25: 🧰 Accesorios y equipamiento | D25: Rejillas y repasadores | E25: bethel | F25: Rejilla pabilo | H25: 1 unidad | I25: RJR010.jpg | J25: 260 | K25: 0.3 | L25: =IF(J25="","",J25*(1+K25)) -> 338 | M25: Activo | O25: Activo | P25: NO | Q25: RJR011 | R25: Rejilla pabilo. Presentación: 1 unidad. | S25: Rejillas y repasadores. Accesorio resistente y práctico, pensado para facilitar las tareas de limpieza del hogar. | T25: ='SUPUESTOS PRECIOS'!$B$9 -> 0 | U25: ='SUPUESTOS PRECIOS'!$B$5/'SUPUESTOS PRECIOS'!$B$4 -> 1000 | V25: =('SUPUESTOS PRECIOS'!$B$6-'SUPUESTOS PRECIOS'!$B$7)/'SUPUESTOS PRECIOS'!$B$4 -> 377.5 | W25: ='SUPUESTOS PRECIOS'!$B$8 -> 0.00968 | X25: ='SUPUESTOS PRECIOS'!$B$2 -> 0.4 | Y25: =IF(OR($B25="",$J25=""),"",ROUND(($J25+$T25+$U25+$V25)/(1-$W25-$X25),-1)) -> 2770 | Z25: =IF($Y25="","",$Y25-$J25-$T25-$U25-$V25-($Y25*$W25)) -> 1105.6864 | AA25: =IF($Y25="","",$Z25/$Y25) -> 0.39916477
A26: 025 | B26: RJR011 | C26: 🧰 Accesorios y equipamiento | D26: Rejillas y repasadores | E26: bethel | F26: Rejilla pabilo | H26: 1 unidad | I26: RJR011.jpg | J26: 300 | K26: 0.3 | L26: =IF(J26="","",J26*(1+K26)) -> 390 | M26: Activo | O26: Activo | P26: NO | Q26: RJR012 | R26: Rejilla pabilo. Presentación: 1 unidad. | S26: Rejillas y repasadores. Accesorio resistente y práctico, pensado para facilitar las tareas de limpieza del hogar. | T26: ='SUPUESTOS PRECIOS'!$B$9 -> 0 | U26: ='SUPUESTOS PRECIOS'!$B$5/'SUPUESTOS PRECIOS'!$B$4 -> 1000 | V26: =('SUPUESTOS PRECIOS'!$B$6-'SUPUESTOS PRECIOS'!$B$7)/'SUPUESTOS PRECIOS'!$B$4 -> 377.5 | W26: ='SUPUESTOS PRECIOS'!$B$8 -> 0.00968 | X26: ='SUPUESTOS PRECIOS'!$B$2 -> 0.4 | Y26: =IF(OR($B26="",$J26=""),"",ROUND(($J26+$T26+$U26+$V26)/(1-$W26-$X26),-1)) -> 2840 | Z26: =IF($Y26="","",$Y26-$J26-$T26-$U26-$V26-($Y26*$W26)) -> 1135.0088 | AA26: =IF($Y26="","",$Z26/$Y26) -> 0.39965099
A27: 026 | B27: RJR012 | C27: 🧰 Accesorios y equipamiento | D27: Rejillas y repasadores | E27: bethel | F27: Rejilla cocina | H27: 1 unidad | I27: RJR012.jpg | J27: 300 | K27: 0.3 | L27: =IF(J27="","",J27*(1+K27)) -> 390 | M27: Activo | O27: Activo | P27: NO | Q27: RJR013 | R27: Rejilla cocina. Presentación: 1 unidad. | S27: Rejillas y repasadores. Accesorio resistente y práctico, pensado para facilitar las tareas de limpieza del hogar. | T27: ='SUPUESTOS PRECIOS'!$B$9 -> 0 | U27: ='SUPUESTOS PRECIOS'!$B$5/'SUPUESTOS PRECIOS'!$B$4 -> 1000 | V27: =('SUPUESTOS PRECIOS'!$B$6-'SUPUESTOS PRECIOS'!$B$7)/'SUPUESTOS PRECIOS'!$B$4 -> 377.5 | W27: ='SUPUESTOS PRECIOS'!$B$8 -> 0.00968 | X27: ='SUPUESTOS PRECIOS'!$B$2 -> 0.4 | Y27: =IF(OR($B27="",$J27=""),"",ROUND(($J27+$T27+$U27+$V27)/(1-$W27-$X27),-1)) -> 2840 | Z27: =IF($Y27="","",$Y27-$J27-$T27-$U27-$V27-($Y27*$W27)) -> 1135.0088 | AA27: =IF($Y27="","",$Z27/$Y27) -> 0.39965099 | AB27: RJR-COCINA | AC27: SIMPLE
A28: 027 | B28: RJR013 | C28: 🧰 Accesorios y equipamiento | D28: Rejillas y repasadores | E28: bethel | F28: Repasador | H28: 1 unidad | I28: RJR013.jpg | J28: 1100 | K28: 0.3 | L28: =IF(J28="","",J28*(1+K28)) -> 1430 | M28: Activo | O28: Activo | P28: NO | Q28: RJR014 | R28: Repasador. Presentación: 1 unidad. | S28: Rejillas y repasadores. Accesorio resistente y práctico, pensado para facilitar las tareas de limpieza del hogar. | T28: ='SUPUESTOS PRECIOS'!$B$9 -> 0 | U28: ='SUPUESTOS PRECIOS'!$B$5/'SUPUESTOS PRECIOS'!$B$4 -> 1000 | V28: =('SUPUESTOS PRECIOS'!$B$6-'SUPUESTOS PRECIOS'!$B$7)/'SUPUESTOS PRECIOS'!$B$4 -> 377.5 | W28: ='SUPUESTOS PRECIOS'!$B$8 -> 0.00968 | X28: ='SUPUESTOS PRECIOS'!$B$2 -> 0.4 | Y28: =IF(OR($B28="",$J28=""),"",ROUND(($J28+$T28+$U28+$V28)/(1-$W28-$X28),-1)) -> 4200 | Z28: =IF($Y28="","",$Y28-$J28-$T28-$U28-$V28-($Y28*$W28)) -> 1681.844 | AA28: =IF($Y28="","",$Z28/$Y28) -> 0.40043905
A29: 028 | B29: RJR014 | C29: 🧰 Accesorios y equipamiento | D29: Rejillas y repasadores | E29: bethel | F29: Repasador | H29: 1 unidad | I29: RJR014.jpg | J29: 1700 | K29: 0.3 | L29: =IF(J29="","",J29*(1+K29)) -> 2210 | M29: Activo | O29: Activo | P29: NO | Q29: RJR015-REPASADOR | R29: Repasador. Presentación: 1 unidad. | S29: Rejillas y repasadores. Accesorio resistente y práctico, pensado para facilitar las tareas de limpieza del hogar. | T29: ='SUPUESTOS PRECIOS'!$B$9 -> 0 | U29: ='SUPUESTOS PRECIOS'!$B$5/'SUPUESTOS PRECIOS'!$B$4 -> 1000 | V29: =('SUPUESTOS PRECIOS'!$B$6-'SUPUESTOS PRECIOS'!$B$7)/'SUPUESTOS PRECIOS'!$B$4 -> 377.5 | W29: ='SUPUESTOS PRECIOS'!$B$8 -> 0.00968 | X29: ='SUPUESTOS PRECIOS'!$B$2 -> 0.4 | Y29: =IF(OR($B29="",$J29=""),"",ROUND(($J29+$T29+$U29+$V29)/(1-$W29-$X29),-1)) -> 5210 | Z29: =IF($Y29="","",$Y29-$J29-$T29-$U29-$V29-($Y29*$W29)) -> 2082.0672 | AA29: =IF($Y29="","",$Z29/$Y29) -> 0.39962902
A30: 029 | B30: RJR015 | C30: 🧰 Accesorios y equipamiento | D30: Rejillas y repasadores | E30: bethel | F30: Paño amarillo para piso | H30: 1 unidad | I30: RJR015.jpg | J30: 600 | K30: 0.3 | L30: =IF(J30="","",J30*(1+K30)) -> 780 | M30: Activo | O30: Activo | P30: NO | Q30: RJR015 | R30: Paño amarillo para piso. Presentación: 1 unidad. | S30: Rejillas y repasadores. Accesorio resistente y práctico, pensado para facilitar las tareas de limpieza del hogar. | T30: ='SUPUESTOS PRECIOS'!$B$9 -> 0 | U30: ='SUPUESTOS PRECIOS'!$B$5/'SUPUESTOS PRECIOS'!$B$4 -> 1000 | V30: =('SUPUESTOS PRECIOS'!$B$6-'SUPUESTOS PRECIOS'!$B$7)/'SUPUESTOS PRECIOS'!$B$4 -> 377.5 | W30: ='SUPUESTOS PRECIOS'!$B$8 -> 0.00968 | X30: ='SUPUESTOS PRECIOS'!$B$2 -> 0.4 | Y30: =IF(OR($B30="",$J30=""),"",ROUND(($J30+$T30+$U30+$V30)/(1-$W30-$X30),-1)) -> 3350 | Z30: =IF($Y30="","",$Y30-$J30-$T30-$U30-$V30-($Y30*$W30)) -> 1340.072 | AA30: =IF($Y30="","",$Z30/$Y30) -> 0.40002149
A31: 030 | B31: TDP001 | C31: 🧰 Accesorios y equipamiento | D31: Trapos de piso | E31: bethel | F31: Trapo de piso blanco | H31: 1 unidad | I31: TDP001.jpg | J31: 1150 | K31: 0.3 | L31: =IF(J31="","",J31*(1+K31)) -> 1495 | M31: Activo | O31: Activo | P31: NO | Q31: TDP001 | R31: Trapo de piso blanco. Presentación: 1 unidad. | S31: Trapos de piso. Accesorio resistente y práctico, pensado para facilitar las tareas de limpieza del hogar. | T31: ='SUPUESTOS PRECIOS'!$B$9 -> 0 | U31: ='SUPUESTOS PRECIOS'!$B$5/'SUPUESTOS PRECIOS'!$B$4 -> 1000 | V31: =('SUPUESTOS PRECIOS'!$B$6-'SUPUESTOS PRECIOS'!$B$7)/'SUPUESTOS PRECIOS'!$B$4 -> 377.5 | W31: ='SUPUESTOS PRECIOS'!$B$8 -> 0.00968 | X31: ='SUPUESTOS PRECIOS'!$B$2 -> 0.4 | Y31: =IF(OR($B31="",$J31=""),"",ROUND(($J31+$T31+$U31+$V31)/(1-$W31-$X31),-1)) -> 4280 | Z31: =IF($Y31="","",$Y31-$J31-$T31-$U31-$V31-($Y31*$W31)) -> 1711.0696 | AA31: =IF($Y31="","",$Z31/$Y31) -> 0.39978262
A32: 031 | B32: TDP002 | C32: 🧰 Accesorios y equipamiento | D32: Trapos de piso | E32: bethel | F32: Trapo de piso gris | H32: 1 unidad | I32: TDP002.jpg | J32: 1150 | K32: 0.3 | L32: =IF(J32="","",J32*(1+K32)) -> 1495 | M32: Activo | O32: Activo | P32: NO | Q32: TDP002 | R32: Trapo de piso gris. Presentación: 1 unidad. | S32: Trapos de piso. Accesorio resistente y práctico, pensado para facilitar las tareas de limpieza del hogar. | T32: ='SUPUESTOS PRECIOS'!$B$9 -> 0 | U32: ='SUPUESTOS PRECIOS'!$B$5/'SUPUESTOS PRECIOS'!$B$4 -> 1000 | V32: =('SUPUESTOS PRECIOS'!$B$6-'SUPUESTOS PRECIOS'!$B$7)/'SUPUESTOS PRECIOS'!$B$4 -> 377.5 | W32: ='SUPUESTOS PRECIOS'!$B$8 -> 0.00968 | X32: ='SUPUESTOS PRECIOS'!$B$2 -> 0.4 | Y32: =IF(OR($B32="",$J32=""),"",ROUND(($J32+$T32+$U32+$V32)/(1-$W32-$X32),-1)) -> 4280 | Z32: =IF($Y32="","",$Y32-$J32-$T32-$U32-$V32-($Y32*$W32)) -> 1711.0696 | AA32: =IF($Y32="","",$Z32/$Y32) -> 0.39978262
A33: 032 | B33: TDP003 | C33: 🧰 Accesorios y equipamiento | D33: Trapos de piso | E33: mr trappo | F33: Trapo de piso costurado | H33: 1 unidad | I33: TDP003.jpg | J33: 1000 | K33: 0.3 | L33: =IF(J33="","",J33*(1+K33)) -> 1300 | M33: Activo | O33: Activo | P33: NO | Q33: TDP003 | R33: Trapo de piso costurado. Presentación: 1 unidad. Marca mr trappo. | S33: Trapos de piso. Accesorio resistente y práctico, pensado para facilitar las tareas de limpieza del hogar. | T33: ='SUPUESTOS PRECIOS'!$B$9 -> 0 | U33: ='SUPUESTOS PRECIOS'!$B$5/'SUPUESTOS PRECIOS'!$B$4 -> 1000 | V33: =('SUPUESTOS PRECIOS'!$B$6-'SUPUESTOS PRECIOS'!$B$7)/'SUPUESTOS PRECIOS'!$B$4 -> 377.5 | W33: ='SUPUESTOS PRECIOS'!$B$8 -> 0.00968 | X33: ='SUPUESTOS PRECIOS'!$B$2 -> 0.4 | Y33: =IF(OR($B33="",$J33=""),"",ROUND(($J33+$T33+$U33+$V33)/(1-$W33-$X33),-1)) -> 4030 | Z33: =IF($Y33="","",$Y33-$J33-$T33-$U33-$V33-($Y33*$W33)) -> 1613.4896 | AA33: =IF($Y33="","",$Z33/$Y33) -> 0.40036963 | AB33: TDP-COSTURADO | AC33: DOBLE
A34: 033 | B34: TDP004 | C34: 🧰 Accesorios y equipamiento | D34: Trapos de piso | E34: Fibran | F34: Trapo de piso costurado | H34: 1 unidad | I34: TDP004.jpg | J34: 650 | K34: 0.3 | L34: =IF(J34="","",J34*(1+K34)) -> 845 | M34: Activo | O34: Activo | P34: NO | Q34: TDP004 | R34: Trapo de piso costurado. Presentación: 1 unidad. Marca Fibran. | S34: Trapos de piso. Accesorio resistente y práctico, pensado para facilitar las tareas de limpieza del hogar. | T34: ='SUPUESTOS PRECIOS'!$B$9 -> 0 | U34: ='SUPUESTOS PRECIOS'!$B$5/'SUPUESTOS PRECIOS'!$B$4 -> 1000 | V34: =('SUPUESTOS PRECIOS'!$B$6-'SUPUESTOS PRECIOS'!$B$7)/'SUPUESTOS PRECIOS'!$B$4 -> 377.5 | W34: ='SUPUESTOS PRECIOS'!$B$8 -> 0.00968 | X34: ='SUPUESTOS PRECIOS'!$B$2 -> 0.4 | Y34: =IF(OR($B34="",$J34=""),"",ROUND(($J34+$T34+$U34+$V34)/(1-$W34-$X34),-1)) -> 3430 | Z34: =IF($Y34="","",$Y34-$J34-$T34-$U34-$V34-($Y34*$W34)) -> 1369.2976 | AA34: =IF($Y34="","",$Z34/$Y34) -> 0.39921213 | AB34: TDP-COSTURADO | AC34: SIMPLE
A35: 034 | B35: TDP005 | C35: 🧰 Accesorios y equipamiento | D35: Trapos de piso | E35: bethel | F35: Trapo de piso nido de abeja | H35: 1 unidad | I35: TDP005.jpg | J35: 1300 | K35: 0.3 | L35: =IF(J35="","",J35*(1+K35)) -> 1690 | M35: Activo | O35: Activo | P35: NO | Q35: TDP005 | R35: Trapo de piso nido de abeja. Presentación: 1 unidad. | S35: Trapos de piso. Accesorio resistente y práctico, pensado para facilitar las tareas de limpieza del hogar. | T35: ='SUPUESTOS PRECIOS'!$B$9 -> 0 | U35: ='SUPUESTOS PRECIOS'!$B$5/'SUPUESTOS PRECIOS'!$B$4 -> 1000 | V35: =('SUPUESTOS PRECIOS'!$B$6-'SUPUESTOS PRECIOS'!$B$7)/'SUPUESTOS PRECIOS'!$B$4 -> 377.5 | W35: ='SUPUESTOS PRECIOS'!$B$8 -> 0.00968 | X35: ='SUPUESTOS PRECIOS'!$B$2 -> 0.4 | Y35: =IF(OR($B35="",$J35=""),"",ROUND(($J35+$T35+$U35+$V35)/(1-$W35-$X35),-1)) -> 4540 | Z35: =IF($Y35="","",$Y35-$J35-$T35-$U35-$V35-($Y35*$W35)) -> 1818.5528 | AA35: =IF($Y35="","",$Z35/$Y35) -> 0.40056229
A36: 035 | B36: TDP006 | C36: 🧰 Accesorios y equipamiento | D36: Trapos de piso | E36: bethel | F36: Trapo de piso nido de abeja economico | H36: 1 unidad | I36: TDP006.jpg | K36: 0.3 | L36: =IF(J36="","",J36*(1+K36)) | M36: Activo | O36: Inactivo | P36: NO | Q36: TDP006 | R36: Trapo de piso nido de abeja economico. Presentación: 1 unidad. | S36: Trapos de piso. Accesorio resistente y práctico, pensado para facilitar las tareas de limpieza del hogar. | T36: ='SUPUESTOS PRECIOS'!$B$9 -> 0 | U36: ='SUPUESTOS PRECIOS'!$B$5/'SUPUESTOS PRECIOS'!$B$4 -> 1000 | V36: =('SUPUESTOS PRECIOS'!$B$6-'SUPUESTOS PRECIOS'!$B$7)/'SUPUESTOS PRECIOS'!$B$4 -> 377.5 | W36: ='SUPUESTOS PRECIOS'!$B$8 -> 0.00968 | X36: ='SUPUESTOS PRECIOS'!$B$2 -> 0.4 | Y36: =IF(OR($B36="",$J36=""),"",ROUND(($J36+$T36+$U36+$V36)/(1-$W36-$X36),-1)) | Z36: =IF($Y36="","",$Y36-$J36-$T36-$U36-$V36-($Y36*$W36)) | AA36: =IF($Y36="","",$Z36/$Y36)
A37: 036 | B37: TDP007 | C37: 🧰 Accesorios y equipamiento | D37: Trapos de piso | E37: consorcio | F37: Trapo de piso rayado | H37: 1 unidad | I37: TDP007.jpg | J37: 1100 | K37: 0.3 | L37: =IF(J37="","",J37*(1+K37)) -> 1430 | M37: Activo | O37: Activo | P37: NO | Q37: TDP007 | R37: Trapo de piso rayado. Presentación: 1 unidad. Marca consorcio. | S37: Trapos de piso. Accesorio resistente y práctico, pensado para facilitar las tareas de limpieza del hogar. | T37: ='SUPUESTOS PRECIOS'!$B$9 -> 0 | U37: ='SUPUESTOS PRECIOS'!$B$5/'SUPUESTOS PRECIOS'!$B$4 -> 1000 | V37: =('SUPUESTOS PRECIOS'!$B$6-'SUPUESTOS PRECIOS'!$B$7)/'SUPUESTOS PRECIOS'!$B$4 -> 377.5 | W37: ='SUPUESTOS PRECIOS'!$B$8 -> 0.00968 | X37: ='SUPUESTOS PRECIOS'!$B$2 -> 0.4 | Y37: =IF(OR($B37="",$J37=""),"",ROUND(($J37+$T37+$U37+$V37)/(1-$W37-$X37),-1)) -> 4200 | Z37: =IF($Y37="","",$Y37-$J37-$T37-$U37-$V37-($Y37*$W37)) -> 1681.844 | AA37: =IF($Y37="","",$Z37/$Y37) -> 0.40043905
A38: 037 | B38: TDP008 | C38: 🧰 Accesorios y equipamiento | D38: Trapos de piso | E38: bethel | F38: Trapo de piso rayado | H38: 1 unidad | I38: TDP008.jpg | J38: 1150 | K38: 0.3 | L38: =IF(J38="","",J38*(1+K38)) -> 1495 | M38: Activo | O38: Activo | P38: NO | Q38: TDP008 | R38: Trapo de piso rayado. Presentación: 1 unidad. | S38: Trapos de piso. Accesorio resistente y práctico, pensado para facilitar las tareas de limpieza del hogar. | T38: ='SUPUESTOS PRECIOS'!$B$9 -> 0 | U38: ='SUPUESTOS PRECIOS'!$B$5/'SUPUESTOS PRECIOS'!$B$4 -> 1000 | V38: =('SUPUESTOS PRECIOS'!$B$6-'SUPUESTOS PRECIOS'!$B$7)/'SUPUESTOS PRECIOS'!$B$4 -> 377.5 | W38: ='SUPUESTOS PRECIOS'!$B$8 -> 0.00968 | X38: ='SUPUESTOS PRECIOS'!$B$2 -> 0.4 | Y38: =IF(OR($B38="",$J38=""),"",ROUND(($J38+$T38+$U38+$V38)/(1-$W38-$X38),-1)) -> 4280 | Z38: =IF($Y38="","",$Y38-$J38-$T38-$U38-$V38-($Y38*$W38)) -> 1711.0696 | AA38: =IF($Y38="","",$Z38/$Y38) -> 0.39978262
A39: 038 | B39: EYE001 | C39: 🧰 Accesorios y equipamiento | D39: Escobas y escobillones | E39: bethel | F39: Escoba Anden de 40 cm | H39: 1 unidad | I39: EYE001.jpg | J39: 5100 | K39: 0.3 | L39: =IF(J39="","",J39*(1+K39)) -> 6630 | M39: Activo | O39: Activo | P39: NO | Q39: EYE001 | R39: Escoba Anden de 40 cm. Presentación: 1 unidad. | S39: Escobas y escobillones. Accesorio resistente y práctico, pensado para facilitar las tareas de limpieza del hogar. | T39: ='SUPUESTOS PRECIOS'!$B$9 -> 0 | U39: ='SUPUESTOS PRECIOS'!$B$5/'SUPUESTOS PRECIOS'!$B$4 -> 1000 | V39: =('SUPUESTOS PRECIOS'!$B$6-'SUPUESTOS PRECIOS'!$B$7)/'SUPUESTOS PRECIOS'!$B$4 -> 377.5 | W39: ='SUPUESTOS PRECIOS'!$B$8 -> 0.00968 | X39: ='SUPUESTOS PRECIOS'!$B$2 -> 0.4 | Y39: =IF(OR($B39="",$J39=""),"",ROUND(($J39+$T39+$U39+$V39)/(1-$W39-$X39),-1)) -> 10970 | Z39: =IF($Y39="","",$Y39-$J39-$T39-$U39-$V39-($Y39*$W39)) -> 4386.3104 | AA39: =IF($Y39="","",$Z39/$Y39) -> 0.39984598 | AB39: EYE-ANDEN | AC39: 40 CM
A40: 039 | B40: EYE002 | C40: 🧰 Accesorios y equipamiento | D40: Escobas y escobillones | E40: bethel | F40: Escoba Anden de 60 cm | H40: 1 unidad | I40: EYE002.jpg | J40: 7200 | K40: 0.3 | L40: =IF(J40="","",J40*(1+K40)) -> 9360 | M40: Activo | O40: Activo | P40: NO | Q40: EYE002 | R40: Escoba Anden de 60 cm. Presentación: 1 unidad. | S40: Escobas y escobillones. Accesorio resistente y práctico, pensado para facilitar las tareas de limpieza del hogar. | T40: ='SUPUESTOS PRECIOS'!$B$9 -> 0 | U40: ='SUPUESTOS PRECIOS'!$B$5/'SUPUESTOS PRECIOS'!$B$4 -> 1000 | V40: =('SUPUESTOS PRECIOS'!$B$6-'SUPUESTOS PRECIOS'!$B$7)/'SUPUESTOS PRECIOS'!$B$4 -> 377.5 | W40: ='SUPUESTOS PRECIOS'!$B$8 -> 0.00968 | X40: ='SUPUESTOS PRECIOS'!$B$2 -> 0.4 | Y40: =IF(OR($B40="",$J40=""),"",ROUND(($J40+$T40+$U40+$V40)/(1-$W40-$X40),-1)) -> 14530 | Z40: =IF($Y40="","",$Y40-$J40-$T40-$U40-$V40-($Y40*$W40)) -> 5811.8496 | AA40: =IF($Y40="","",$Z40/$Y40) -> 0.39998965 | AB40: EYE-ANDEN | AC40: 60 CM
A41: 040 | B41: EYE003 | C41: 🧰 Accesorios y equipamiento | D41: Escobas y escobillones | E41: bethel | F41: Escoba Anden de 80 cm | H41: 1 unidad | I41: EYE003.jpg | J41: 8900 | K41: 0.3 | L41: =IF(J41="","",J41*(1+K41)) -> 11570 | M41: Activo | O41: Activo | P41: NO | Q41: EYE003 | R41: Escoba Anden de 80 cm. Presentación: 1 unidad. | S41: Escobas y escobillones. Accesorio resistente y práctico, pensado para facilitar las tareas de limpieza del hogar. | T41: ='SUPUESTOS PRECIOS'!$B$9 -> 0 | U41: ='SUPUESTOS PRECIOS'!$B$5/'SUPUESTOS PRECIOS'!$B$4 -> 1000 | V41: =('SUPUESTOS PRECIOS'!$B$6-'SUPUESTOS PRECIOS'!$B$7)/'SUPUESTOS PRECIOS'!$B$4 -> 377.5 | W41: ='SUPUESTOS PRECIOS'!$B$8 -> 0.00968 | X41: ='SUPUESTOS PRECIOS'!$B$2 -> 0.4 | Y41: =IF(OR($B41="",$J41=""),"",ROUND(($J41+$T41+$U41+$V41)/(1-$W41-$X41),-1)) -> 17410 | Z41: =IF($Y41="","",$Y41-$J41-$T41-$U41-$V41-($Y41*$W41)) -> 6963.9712 | AA41: =IF($Y41="","",$Z41/$Y41) -> 0.39999835 | AB41: EYE-ANDEN | AC41: 80 CM
A42: 041 | B42: EYE004 | C42: 🧰 Accesorios y equipamiento | D42: Escobas y escobillones | E42: bethel | F42: Escoba Anden de 100 cm | H42: 1 unidad | I42: EYE004.jpg | J42: 11500 | K42: 0.3 | L42: =IF(J42="","",J42*(1+K42)) -> 14950 | M42: Activo | O42: Activo | P42: NO | Q42: EYE004 | R42: Escoba Anden de 100 cm. Presentación: 1 unidad. | S42: Escobas y escobillones. Accesorio resistente y práctico, pensado para facilitar las tareas de limpieza del hogar. | T42: ='SUPUESTOS PRECIOS'!$B$9 -> 0 | U42: ='SUPUESTOS PRECIOS'!$B$5/'SUPUESTOS PRECIOS'!$B$4 -> 1000 | V42: =('SUPUESTOS PRECIOS'!$B$6-'SUPUESTOS PRECIOS'!$B$7)/'SUPUESTOS PRECIOS'!$B$4 -> 377.5 | W42: ='SUPUESTOS PRECIOS'!$B$8 -> 0.00968 | X42: ='SUPUESTOS PRECIOS'!$B$2 -> 0.4 | Y42: =IF(OR($B42="",$J42=""),"",ROUND(($J42+$T42+$U42+$V42)/(1-$W42-$X42),-1)) -> 21810 | Z42: =IF($Y42="","",$Y42-$J42-$T42-$U42-$V42-($Y42*$W42)) -> 8721.3792 | AA42: =IF($Y42="","",$Z42/$Y42) -> 0.39987983 | AB42: EYE-ANDEN | AC42: 100 CM
A43: 042 | B43: EYE005 | C43: 🧰 Accesorios y equipamiento | D43: Escobas y escobillones | E43: bethel | F43: Escoba Anden de 60 cm barregrueso | H43: 1 unidad | I43: EYE005.jpg | J43: 6200 | K43: 0.3 | L43: =IF(J43="","",J43*(1+K43)) -> 8060 | M43: Activo | O43: Activo | P43: NO | Q43: EYE005 | R43: Escoba Anden de 60 cm barregrueso. Presentación: 1 unidad. | S43: Escobas y escobillones. Accesorio resistente y práctico, pensado para facilitar las tareas de limpieza del hogar. | T43: ='SUPUESTOS PRECIOS'!$B$9 -> 0 | U43: ='SUPUESTOS PRECIOS'!$B$5/'SUPUESTOS PRECIOS'!$B$4 -> 1000 | V43: =('SUPUESTOS PRECIOS'!$B$6-'SUPUESTOS PRECIOS'!$B$7)/'SUPUESTOS PRECIOS'!$B$4 -> 377.5 | W43: ='SUPUESTOS PRECIOS'!$B$8 -> 0.00968 | X43: ='SUPUESTOS PRECIOS'!$B$2 -> 0.4 | Y43: =IF(OR($B43="",$J43=""),"",ROUND(($J43+$T43+$U43+$V43)/(1-$W43-$X43),-1)) -> 12840 | Z43: =IF($Y43="","",$Y43-$J43-$T43-$U43-$V43-($Y43*$W43)) -> 5138.2088 | AA43: =IF($Y43="","",$Z43/$Y43) -> 0.40017202
A44: 043 | B44: EYE006 | C44: 🧰 Accesorios y equipamiento | D44: Escobas y escobillones | E44: bethel | F44: Escobillon Barrendero Economico | H44: 1 unidad | I44: EYE006.jpg | J44: 7100 | K44: 0.3 | L44: =IF(J44="","",J44*(1+K44)) -> 9230 | M44: Activo | O44: Activo | P44: NO | Q44: EYE006 | R44: Escobillon Barrendero Economico. Presentación: 1 unidad. | S44: Escobas y escobillones. Accesorio resistente y práctico, pensado para facilitar las tareas de limpieza del hogar. | T44: ='SUPUESTOS PRECIOS'!$B$9 -> 0 | U44: ='SUPUESTOS PRECIOS'!$B$5/'SUPUESTOS PRECIOS'!$B$4 -> 1000 | V44: =('SUPUESTOS PRECIOS'!$B$6-'SUPUESTOS PRECIOS'!$B$7)/'SUPUESTOS PRECIOS'!$B$4 -> 377.5 | W44: ='SUPUESTOS PRECIOS'!$B$8 -> 0.00968 | X44: ='SUPUESTOS PRECIOS'!$B$2 -> 0.4 | Y44: =IF(OR($B44="",$J44=""),"",ROUND(($J44+$T44+$U44+$V44)/(1-$W44-$X44),-1)) -> 14360 | Z44: =IF($Y44="","",$Y44-$J44-$T44-$U44-$V44-($Y44*$W44)) -> 5743.4952 | AA44: =IF($Y44="","",$Z44/$Y44) -> 0.39996485
A45: 044 | B45: EYE007 | C45: 🧰 Accesorios y equipamiento | D45: Escobas y escobillones | E45: bethel | F45: Escoba tipo barredor de 35 cm | H45: 1 unidad | I45: EYE007.jpg | J45: 5500 | K45: 0.3 | L45: =IF(J45="","",J45*(1+K45)) -> 7150 | M45: Activo | O45: Activo | P45: NO | Q45: EYE007 | R45: Escoba tipo barredor de 35 cm. Presentación: 1 unidad. | S45: Escobas y escobillones. Accesorio resistente y práctico, pensado para facilitar las tareas de limpieza del hogar. | T45: ='SUPUESTOS PRECIOS'!$B$9 -> 0 | U45: ='SUPUESTOS PRECIOS'!$B$5/'SUPUESTOS PRECIOS'!$B$4 -> 1000 | V45: =('SUPUESTOS PRECIOS'!$B$6-'SUPUESTOS PRECIOS'!$B$7)/'SUPUESTOS PRECIOS'!$B$4 -> 377.5 | W45: ='SUPUESTOS PRECIOS'!$B$8 -> 0.00968 | X45: ='SUPUESTOS PRECIOS'!$B$2 -> 0.4 | Y45: =IF(OR($B45="",$J45=""),"",ROUND(($J45+$T45+$U45+$V45)/(1-$W45-$X45),-1)) -> 11650 | Z45: =IF($Y45="","",$Y45-$J45-$T45-$U45-$V45-($Y45*$W45)) -> 4659.728 | AA45: =IF($Y45="","",$Z45/$Y45) -> 0.39997665 | AB45: EYE-BARREDOR | AC45: 35 CM
A46: 045 | B46: EYE008 | C46: 🧰 Accesorios y equipamiento | D46: Escobas y escobillones | E46: bethel | F46: Escoba tipo barredor de 60 cm | H46: 1 unidad | I46: EYE008.jpg | J46: 7000 | K46: 0.3 | L46: =IF(J46="","",J46*(1+K46)) -> 9100 | M46: Activo | O46: Activo | P46: NO | Q46: EYE008 | R46: Escoba tipo barredor de 60 cm. Presentación: 1 unidad. | S46: Escobas y escobillones. Accesorio resistente y práctico, pensado para facilitar las tareas de limpieza del hogar. | T46: ='SUPUESTOS PRECIOS'!$B$9 -> 0 | U46: ='SUPUESTOS PRECIOS'!$B$5/'SUPUESTOS PRECIOS'!$B$4 -> 1000 | V46: =('SUPUESTOS PRECIOS'!$B$6-'SUPUESTOS PRECIOS'!$B$7)/'SUPUESTOS PRECIOS'!$B$4 -> 377.5 | W46: ='SUPUESTOS PRECIOS'!$B$8 -> 0.00968 | X46: ='SUPUESTOS PRECIOS'!$B$2 -> 0.4 | Y46: =IF(OR($B46="",$J46=""),"",ROUND(($J46+$T46+$U46+$V46)/(1-$W46-$X46),-1)) -> 14190 | Z46: =IF($Y46="","",$Y46-$J46-$T46-$U46-$V46-($Y46*$W46)) -> 5675.1408 | AA46: =IF($Y46="","",$Z46/$Y46) -> 0.39993945 | AB46: EYE-BARREDOR | AC46: 60 CM
A47: 046 | B47: EYE009 | C47: 🧰 Accesorios y equipamiento | D47: Escobas y escobillones | E47: bethel | F47: Escoba tipo barredor de 80 cm | H47: 1 unidad | I47: EYE009.jpg | J47: 8000 | K47: 0.3 | L47: =IF(J47="","",J47*(1+K47)) -> 10400 | M47: Activo | O47: Activo | P47: NO | Q47: EYE009 | R47: Escoba tipo barredor de 80 cm. Presentación: 1 unidad. | S47: Escobas y escobillones. Accesorio resistente y práctico, pensado para facilitar las tareas de limpieza del hogar. | T47: ='SUPUESTOS PRECIOS'!$B$9 -> 0 | U47: ='SUPUESTOS PRECIOS'!$B$5/'SUPUESTOS PRECIOS'!$B$4 -> 1000 | V47: =('SUPUESTOS PRECIOS'!$B$6-'SUPUESTOS PRECIOS'!$B$7)/'SUPUESTOS PRECIOS'!$B$4 -> 377.5 | W47: ='SUPUESTOS PRECIOS'!$B$8 -> 0.00968 | X47: ='SUPUESTOS PRECIOS'!$B$2 -> 0.4 | Y47: =IF(OR($B47="",$J47=""),"",ROUND(($J47+$T47+$U47+$V47)/(1-$W47-$X47),-1)) -> 15890 | Z47: =IF($Y47="","",$Y47-$J47-$T47-$U47-$V47-($Y47*$W47)) -> 6358.6848 | AA47: =IF($Y47="","",$Z47/$Y47) -> 0.40016896 | AB47: EYE-BARREDOR | AC47: 80 CM
A48: 047 | B48: EYE010 | C48: 🧰 Accesorios y equipamiento | D48: Escobas y escobillones | E48: bethel | F48: Escoba tipo barredor de 100 cm | H48: 1 unidad | I48: EYE010.jpg | J48: 9900 | K48: 0.3 | L48: =IF(J48="","",J48*(1+K48)) -> 12870 | M48: Activo | O48: Activo | P48: NO | Q48: EYE010 | R48: Escoba tipo barredor de 100 cm. Presentación: 1 unidad. | S48: Escobas y escobillones. Accesorio resistente y práctico, pensado para facilitar las tareas de limpieza del hogar. | T48: ='SUPUESTOS PRECIOS'!$B$9 -> 0 | U48: ='SUPUESTOS PRECIOS'!$B$5/'SUPUESTOS PRECIOS'!$B$4 -> 1000 | V48: =('SUPUESTOS PRECIOS'!$B$6-'SUPUESTOS PRECIOS'!$B$7)/'SUPUESTOS PRECIOS'!$B$4 -> 377.5 | W48: ='SUPUESTOS PRECIOS'!$B$8 -> 0.00968 | X48: ='SUPUESTOS PRECIOS'!$B$2 -> 0.4 | Y48: =IF(OR($B48="",$J48=""),"",ROUND(($J48+$T48+$U48+$V48)/(1-$W48-$X48),-1)) -> 19100 | Z48: =IF($Y48="","",$Y48-$J48-$T48-$U48-$V48-($Y48*$W48)) -> 7637.612 | AA48: =IF($Y48="","",$Z48/$Y48) -> 0.39987497 | AB48: EYE-BARREDOR | AC48: 100 CM
A49: 048 | B49: EYE011 | C49: 🧰 Accesorios y equipamiento | D49: Escobas y escobillones | E49: bethel | F49: Barre Hojas Comun | H49: 1 unidad | I49: EYE011.jpg | J49: 1800 | K49: 0.3 | L49: =IF(J49="","",J49*(1+K49)) -> 2340 | M49: Activo | O49: Activo | P49: NO | Q49: EYE011 | R49: Barre Hojas Comun. Presentación: 1 unidad. | S49: Escobas y escobillones. Accesorio resistente y práctico, pensado para facilitar las tareas de limpieza del hogar. | T49: ='SUPUESTOS PRECIOS'!$B$9 -> 0 | U49: ='SUPUESTOS PRECIOS'!$B$5/'SUPUESTOS PRECIOS'!$B$4 -> 1000 | V49: =('SUPUESTOS PRECIOS'!$B$6-'SUPUESTOS PRECIOS'!$B$7)/'SUPUESTOS PRECIOS'!$B$4 -> 377.5 | W49: ='SUPUESTOS PRECIOS'!$B$8 -> 0.00968 | X49: ='SUPUESTOS PRECIOS'!$B$2 -> 0.4 | Y49: =IF(OR($B49="",$J49=""),"",ROUND(($J49+$T49+$U49+$V49)/(1-$W49-$X49),-1)) -> 5380 | Z49: =IF($Y49="","",$Y49-$J49-$T49-$U49-$V49-($Y49*$W49)) -> 2150.4216 | AA49: =IF($Y49="","",$Z49/$Y49) -> 0.39970662
A50: 049 | B50: EYE012 | C50: 🧰 Accesorios y equipamiento | D50: Escobas y escobillones | E50: bethel | F50: Barre Hojas Profesional | H50: 1 unidad | I50: EYE012.jpg | J50: 2900 | K50: 0.3 | L50: =IF(J50="","",J50*(1+K50)) -> 3770 | M50: Activo | O50: Activo | P50: NO | Q50: EYE012 | R50: Barre Hojas Profesional. Presentación: 1 unidad. | S50: Escobas y escobillones. Accesorio resistente y práctico, pensado para facilitar las tareas de limpieza del hogar. | T50: ='SUPUESTOS PRECIOS'!$B$9 -> 0 | U50: ='SUPUESTOS PRECIOS'!$B$5/'SUPUESTOS PRECIOS'!$B$4 -> 1000 | V50: =('SUPUESTOS PRECIOS'!$B$6-'SUPUESTOS PRECIOS'!$B$7)/'SUPUESTOS PRECIOS'!$B$4 -> 377.5 | W50: ='SUPUESTOS PRECIOS'!$B$8 -> 0.00968 | X50: ='SUPUESTOS PRECIOS'!$B$2 -> 0.4 | Y50: =IF(OR($B50="",$J50=""),"",ROUND(($J50+$T50+$U50+$V50)/(1-$W50-$X50),-1)) -> 7250 | Z50: =IF($Y50="","",$Y50-$J50-$T50-$U50-$V50-($Y50*$W50)) -> 2902.32 | AA50: =IF($Y50="","",$Z50/$Y50) -> 0.40032
A51: 050 | B51: EYE013 | C51: 🧰 Accesorios y equipamiento | D51: Escobas y escobillones | E51: bethel | F51: Escoba de tipo 6 hilos | H51: 1 unidad | I51: EYE013.jpg | J51: 6500 | K51: 0.3 | L51: =IF(J51="","",J51*(1+K51)) -> 8450 | M51: Activo | O51: Activo | P51: NO | Q51: EYE013 | R51: Escoba de tipo 6 hilos. Presentación: 1 unidad. | S51: Escobas y escobillones. Accesorio resistente y práctico, pensado para facilitar las tareas de limpieza del hogar. | T51: ='SUPUESTOS PRECIOS'!$B$9 -> 0 | U51: ='SUPUESTOS PRECIOS'!$B$5/'SUPUESTOS PRECIOS'!$B$4 -> 1000 | V51: =('SUPUESTOS PRECIOS'!$B$6-'SUPUESTOS PRECIOS'!$B$7)/'SUPUESTOS PRECIOS'!$B$4 -> 377.5 | W51: ='SUPUESTOS PRECIOS'!$B$8 -> 0.00968 | X51: ='SUPUESTOS PRECIOS'!$B$2 -> 0.4 | Y51: =IF(OR($B51="",$J51=""),"",ROUND(($J51+$T51+$U51+$V51)/(1-$W51-$X51),-1)) -> 13340 | Z51: =IF($Y51="","",$Y51-$J51-$T51-$U51-$V51-($Y51*$W51)) -> 5333.3688 | AA51: =IF($Y51="","",$Z51/$Y51) -> 0.39980276
A52: 051 | B52: EYE014 | C52: 🧰 Accesorios y equipamiento | D52: Escobas y escobillones | E52: bethel | F52: Escoba de tipo Americana | H52: 1 unidad | I52: EYE014.jpg | J52: 2000 | K52: 0.3 | L52: =IF(J52="","",J52*(1+K52)) -> 2600 | M52: Activo | O52: Activo | P52: NO | Q52: EYE014 | R52: Escoba de tipo Americana. Presentación: 1 unidad. | S52: Escobas y escobillones. Accesorio resistente y práctico, pensado para facilitar las tareas de limpieza del hogar. | T52: ='SUPUESTOS PRECIOS'!$B$9 -> 0 | U52: ='SUPUESTOS PRECIOS'!$B$5/'SUPUESTOS PRECIOS'!$B$4 -> 1000 | V52: =('SUPUESTOS PRECIOS'!$B$6-'SUPUESTOS PRECIOS'!$B$7)/'SUPUESTOS PRECIOS'!$B$4 -> 377.5 | W52: ='SUPUESTOS PRECIOS'!$B$8 -> 0.00968 | X52: ='SUPUESTOS PRECIOS'!$B$2 -> 0.4 | Y52: =IF(OR($B52="",$J52=""),"",ROUND(($J52+$T52+$U52+$V52)/(1-$W52-$X52),-1)) -> 5720 | Z52: =IF($Y52="","",$Y52-$J52-$T52-$U52-$V52-($Y52*$W52)) -> 2287.1304 | AA52: =IF($Y52="","",$Z52/$Y52) -> 0.39984797
A53: 052 | B53: EYE015 | C53: 🧰 Accesorios y equipamiento | D53: Escobas y escobillones | E53: bethel | F53: Escoba de tipo Capuchina | H53: 1 unidad | I53: EYE015.jpg | J53: 2600 | K53: 0.3 | L53: =IF(J53="","",J53*(1+K53)) -> 3380 | M53: Activo | O53: Activo | P53: NO | Q53: EYE015 | R53: Escoba de tipo Capuchina. Presentación: 1 unidad. | S53: Escobas y escobillones. Accesorio resistente y práctico, pensado para facilitar las tareas de limpieza del hogar. | T53: ='SUPUESTOS PRECIOS'!$B$9 -> 0 | U53: ='SUPUESTOS PRECIOS'!$B$5/'SUPUESTOS PRECIOS'!$B$4 -> 1000 | V53: =('SUPUESTOS PRECIOS'!$B$6-'SUPUESTOS PRECIOS'!$B$7)/'SUPUESTOS PRECIOS'!$B$4 -> 377.5 | W53: ='SUPUESTOS PRECIOS'!$B$8 -> 0.00968 | X53: ='SUPUESTOS PRECIOS'!$B$2 -> 0.4 | Y53: =IF(OR($B53="",$J53=""),"",ROUND(($J53+$T53+$U53+$V53)/(1-$W53-$X53),-1)) -> 6740 | Z53: =IF($Y53="","",$Y53-$J53-$T53-$U53-$V53-($Y53*$W53)) -> 2697.2568 | AA53: =IF($Y53="","",$Z53/$Y53) -> 0.40018647
A54: 053 | B54: EYE016 | C54: 🧰 Accesorios y equipamiento | D54: Escobas y escobillones | E54: bethel | F54: Escoba de tipo Barregrueso | H54: 1 unidad | I54: EYE016.jpg | J54: 2000 | K54: 0.3 | L54: =IF(J54="","",J54*(1+K54)) -> 2600 | M54: Activo | O54: Activo | P54: NO | Q54: EYE016 | R54: Escoba de tipo Barregrueso. Presentación: 1 unidad. | S54: Escobas y escobillones. Accesorio resistente y práctico, pensado para facilitar las tareas de limpieza del hogar. | T54: ='SUPUESTOS PRECIOS'!$B$9 -> 0 | U54: ='SUPUESTOS PRECIOS'!$B$5/'SUPUESTOS PRECIOS'!$B$4 -> 1000 | V54: =('SUPUESTOS PRECIOS'!$B$6-'SUPUESTOS PRECIOS'!$B$7)/'SUPUESTOS PRECIOS'!$B$4 -> 377.5 | W54: ='SUPUESTOS PRECIOS'!$B$8 -> 0.00968 | X54: ='SUPUESTOS PRECIOS'!$B$2 -> 0.4 | Y54: =IF(OR($B54="",$J54=""),"",ROUND(($J54+$T54+$U54+$V54)/(1-$W54-$X54),-1)) -> 5720 | Z54: =IF($Y54="","",$Y54-$J54-$T54-$U54-$V54-($Y54*$W54)) -> 2287.1304 | AA54: =IF($Y54="","",$Z54/$Y54) -> 0.39984797
A55: 054 | B55: EYE017 | C55: 🧰 Accesorios y equipamiento | D55: Escobas y escobillones | E55: bethel | F55: Escobillon de tipo liso de Cerda | H55: 1 unidad | I55: EYE017.jpg | J55: 9100 | K55: 0.3 | L55: =IF(J55="","",J55*(1+K55)) -> 11830 | M55: Activo | O55: Activo | P55: NO | Q55: EYE017 | R55: Escobillon de tipo liso de Cerda. Presentación: 1 unidad. | S55: Escobas y escobillones. Accesorio resistente y práctico, pensado para facilitar las tareas de limpieza del hogar. | T55: ='SUPUESTOS PRECIOS'!$B$9 -> 0 | U55: ='SUPUESTOS PRECIOS'!$B$5/'SUPUESTOS PRECIOS'!$B$4 -> 1000 | V55: =('SUPUESTOS PRECIOS'!$B$6-'SUPUESTOS PRECIOS'!$B$7)/'SUPUESTOS PRECIOS'!$B$4 -> 377.5 | W55: ='SUPUESTOS PRECIOS'!$B$8 -> 0.00968 | X55: ='SUPUESTOS PRECIOS'!$B$2 -> 0.4 | Y55: =IF(OR($B55="",$J55=""),"",ROUND(($J55+$T55+$U55+$V55)/(1-$W55-$X55),-1)) -> 17750 | Z55: =IF($Y55="","",$Y55-$J55-$T55-$U55-$V55-($Y55*$W55)) -> 7100.68 | AA55: =IF($Y55="","",$Z55/$Y55) -> 0.40003831
A56: 055 | B56: EYE018 | C56: 🧰 Accesorios y equipamiento | D56: Escobas y escobillones | E56: bethel | F56: Escoba de tipo Galponera | H56: 1 unidad | I56: EYE018.jpg | J56: 3000 | K56: 0.3 | L56: =IF(J56="","",J56*(1+K56)) -> 3900 | M56: Activo | O56: Activo | P56: NO | Q56: EYE018 | R56: Escoba de tipo Galponera. Presentación: 1 unidad. | S56: Escobas y escobillones. Accesorio resistente y práctico, pensado para facilitar las tareas de limpieza del hogar. | T56: ='SUPUESTOS PRECIOS'!$B$9 -> 0 | U56: ='SUPUESTOS PRECIOS'!$B$5/'SUPUESTOS PRECIOS'!$B$4 -> 1000 | V56: =('SUPUESTOS PRECIOS'!$B$6-'SUPUESTOS PRECIOS'!$B$7)/'SUPUESTOS PRECIOS'!$B$4 -> 377.5 | W56: ='SUPUESTOS PRECIOS'!$B$8 -> 0.00968 | X56: ='SUPUESTOS PRECIOS'!$B$2 -> 0.4 | Y56: =IF(OR($B56="",$J56=""),"",ROUND(($J56+$T56+$U56+$V56)/(1-$W56-$X56),-1)) -> 7420 | Z56: =IF($Y56="","",$Y56-$J56-$T56-$U56-$V56-($Y56*$W56)) -> 2970.6744 | AA56: =IF($Y56="","",$Z56/$Y56) -> 0.40036043
A57: 056 | B57: EYE019 | C57: 🧰 Accesorios y equipamiento | D57: Escobas y escobillones | E57: Rey Laqueado | F57: Escobillon Rey Laqueado | H57: 1 unidad | I57: EYE019.jpg | J57: 3000 | K57: 0.3 | L57: =IF(J57="","",J57*(1+K57)) -> 3900 | M57: Activo | O57: Activo | P57: NO | Q57: EYE019 | R57: Escobillon Rey Laqueado. Presentación: 1 unidad. Marca Rey Laqueado. | S57: Escobas y escobillones. Accesorio resistente y práctico, pensado para facilitar las tareas de limpieza del hogar. | T57: ='SUPUESTOS PRECIOS'!$B$9 -> 0 | U57: ='SUPUESTOS PRECIOS'!$B$5/'SUPUESTOS PRECIOS'!$B$4 -> 1000 | V57: =('SUPUESTOS PRECIOS'!$B$6-'SUPUESTOS PRECIOS'!$B$7)/'SUPUESTOS PRECIOS'!$B$4 -> 377.5 | W57: ='SUPUESTOS PRECIOS'!$B$8 -> 0.00968 | X57: ='SUPUESTOS PRECIOS'!$B$2 -> 0.4 | Y57: =IF(OR($B57="",$J57=""),"",ROUND(($J57+$T57+$U57+$V57)/(1-$W57-$X57),-1)) -> 7420 | Z57: =IF($Y57="","",$Y57-$J57-$T57-$U57-$V57-($Y57*$W57)) -> 2970.6744 | AA57: =IF($Y57="","",$Z57/$Y57) -> 0.40036043
A58: 057 | B58: EYE020 | C58: 🧰 Accesorios y equipamiento | D58: Escobas y escobillones | E58: bethel | F58: Escobillon tipo princesa laqueado | H58: 1 unidad | I58: EYE020.jpg | J58: 4200 | K58: 0.3 | L58: =IF(J58="","",J58*(1+K58)) -> 5460 | M58: Activo | O58: Activo | P58: NO | Q58: EYE020 | R58: Escobillon tipo princesa laqueado. Presentación: 1 unidad. | S58: Escobas y escobillones. Accesorio resistente y práctico, pensado para facilitar las tareas de limpieza del hogar. | T58: ='SUPUESTOS PRECIOS'!$B$9 -> 0 | U58: ='SUPUESTOS PRECIOS'!$B$5/'SUPUESTOS PRECIOS'!$B$4 -> 1000 | V58: =('SUPUESTOS PRECIOS'!$B$6-'SUPUESTOS PRECIOS'!$B$7)/'SUPUESTOS PRECIOS'!$B$4 -> 377.5 | W58: ='SUPUESTOS PRECIOS'!$B$8 -> 0.00968 | X58: ='SUPUESTOS PRECIOS'!$B$2 -> 0.4 | Y58: =IF(OR($B58="",$J58=""),"",ROUND(($J58+$T58+$U58+$V58)/(1-$W58-$X58),-1)) -> 9450 | Z58: =IF($Y58="","",$Y58-$J58-$T58-$U58-$V58-($Y58*$W58)) -> 3781.024 | AA58: =IF($Y58="","",$Z58/$Y58) -> 0.40010836
A59: 058 | B59: EYE021 | C59: 🧰 Accesorios y equipamiento | D59: Escobas y escobillones | E59: bethel | F59: Escobillon tipo barregrueso economico | H59: 1 unidad | I59: EYE021.jpg | J59: 3100 | K59: 0.3 | L59: =IF(J59="","",J59*(1+K59)) -> 4030 | M59: Activo | O59: Activo | P59: NO | Q59: EYE021 | R59: Escobillon tipo barregrueso economico. Presentación: 1 unidad. | S59: Escobas y escobillones. Accesorio resistente y práctico, pensado para facilitar las tareas de limpieza del hogar. | T59: ='SUPUESTOS PRECIOS'!$B$9 -> 0 | U59: ='SUPUESTOS PRECIOS'!$B$5/'SUPUESTOS PRECIOS'!$B$4 -> 1000 | V59: =('SUPUESTOS PRECIOS'!$B$6-'SUPUESTOS PRECIOS'!$B$7)/'SUPUESTOS PRECIOS'!$B$4 -> 377.5 | W59: ='SUPUESTOS PRECIOS'!$B$8 -> 0.00968 | X59: ='SUPUESTOS PRECIOS'!$B$2 -> 0.4 | Y59: =IF(OR($B59="",$J59=""),"",ROUND(($J59+$T59+$U59+$V59)/(1-$W59-$X59),-1)) -> 7580 | Z59: =IF($Y59="","",$Y59-$J59-$T59-$U59-$V59-($Y59*$W59)) -> 3029.1256 | AA59: =IF($Y59="","",$Z59/$Y59) -> 0.39962079
A60: 059 | B60: EYE022 | C60: 🧰 Accesorios y equipamiento | D60: Escobas y escobillones | E60: bethel | F60: Escobillon tipo barregrueso salzano | H60: 1 unidad | I60: EYE022.jpg | J60: 4000 | K60: 0.3 | L60: =IF(J60="","",J60*(1+K60)) -> 5200 | M60: Activo | O60: Activo | P60: NO | Q60: EYE022 | R60: Escobillon tipo barregrueso salzano. Presentación: 1 unidad. | S60: Escobas y escobillones. Accesorio resistente y práctico, pensado para facilitar las tareas de limpieza del hogar. | T60: ='SUPUESTOS PRECIOS'!$B$9 -> 0 | U60: ='SUPUESTOS PRECIOS'!$B$5/'SUPUESTOS PRECIOS'!$B$4 -> 1000 | V60: =('SUPUESTOS PRECIOS'!$B$6-'SUPUESTOS PRECIOS'!$B$7)/'SUPUESTOS PRECIOS'!$B$4 -> 377.5 | W60: ='SUPUESTOS PRECIOS'!$B$8 -> 0.00968 | X60: ='SUPUESTOS PRECIOS'!$B$2 -> 0.4 | Y60: =IF(OR($B60="",$J60=""),"",ROUND(($J60+$T60+$U60+$V60)/(1-$W60-$X60),-1)) -> 9110 | Z60: =IF($Y60="","",$Y60-$J60-$T60-$U60-$V60-($Y60*$W60)) -> 3644.3152 | AA60: =IF($Y60="","",$Z60/$Y60) -> 0.4000346
... A71: 070 | B71: EYE033 | C71: 🧰 Accesorios y equipamiento | D71: Escobas y escobillones | E71: bethel | F71: Globo de Techo Punky | H71: 1 unidad | I71: EYE033.jpg | J71: 2700 | K71: 0.3 | L71: =IF(J71="","",J71*(1+K71)) -> 3510 | M71: Activo | O71: Activo | P71: NO | Q71: EYE033 | R71: Globo de Techo Punky. Presentación: 1 unidad. | S71: Escobas y escobillones. Accesorio resistente y práctico, pensado para facilitar las tareas de limpieza del hogar. | T71: ='SUPUESTOS PRECIOS'!$B$9 -> 0 | U71: ='SUPUESTOS PRECIOS'!$B$5/'SUPUESTOS PRECIOS'!$B$4 -> 1000 | V71: =('SUPUESTOS PRECIOS'!$B$6-'SUPUESTOS PRECIOS'!$B$7)/'SUPUESTOS PRECIOS'!$B$4 -> 377.5 | W71: ='SUPUESTOS PRECIOS'!$B$8 -> 0.00968 | X71: ='SUPUESTOS PRECIOS'!$B$2 -> 0.4 | Y71: =IF(OR($B71="",$J71=""),"",ROUND(($J71+$T71+$U71+$V71)/(1-$W71-$X71),-1)) -> 6910 | Z71: =IF($Y71="","",$Y71-$J71-$T71-$U71-$V71-($Y71*$W71)) -> 2765.6112 | AA71: =IF($Y71="","",$Z71/$Y71) -> 0.40023317
A72: 071 | B72: EYE034 | C72: 🧰 Accesorios y equipamiento | D72: Escobas y escobillones | E72: bethel | F72: Repuesto barredor | H72: 1 unidad | I72: EYE034.jpg | J72: 2600 | K72: 0.3 | L72: =IF(J72="","",J72*(1+K72)) -> 3380 | M72: Activo | O72: Activo | P72: NO | Q72: EYE034 | R72: Repuesto barredor. Presentación: 1 unidad. | S72: Escobas y escobillones. Accesorio resistente y práctico, pensado para facilitar las tareas de limpieza del hogar. | T72: ='SUPUESTOS PRECIOS'!$B$9 -> 0 | U72: ='SUPUESTOS PRECIOS'!$B$5/'SUPUESTOS PRECIOS'!$B$4 -> 1000 | V72: =('SUPUESTOS PRECIOS'!$B$6-'SUPUESTOS PRECIOS'!$B$7)/'SUPUESTOS PRECIOS'!$B$4 -> 377.5 | W72: ='SUPUESTOS PRECIOS'!$B$8 -> 0.00968 | X72: ='SUPUESTOS PRECIOS'!$B$2 -> 0.4 | Y72: =IF(OR($B72="",$J72=""),"",ROUND(($J72+$T72+$U72+$V72)/(1-$W72-$X72),-1)) -> 6740 | Z72: =IF($Y72="","",$Y72-$J72-$T72-$U72-$V72-($Y72*$W72)) -> 2697.2568 | AA72: =IF($Y72="","",$Z72/$Y72) -> 0.40018647 | AB72: EYE-BARREDOR | AC72: 35 CM
A73: 072 | B73: EYE035 | C73: 🧰 Accesorios y equipamiento | D73: Escobas y escobillones | E73: bethel | F73: Repuesto barredor | H73: 1 unidad | I73: EYE035.jpg | J73: 3700 | K73: 0.3 | L73: =IF(J73="","",J73*(1+K73)) -> 4810 | M73: Activo | O73: Activo | P73: NO | Q73: EYE035 | R73: Repuesto barredor. Presentación: 1 unidad. | S73: Escobas y escobillones. Accesorio resistente y práctico, pensado para facilitar las tareas de limpieza del hogar. | T73: ='SUPUESTOS PRECIOS'!$B$9 -> 0 | U73: ='SUPUESTOS PRECIOS'!$B$5/'SUPUESTOS PRECIOS'!$B$4 -> 1000 | V73: =('SUPUESTOS PRECIOS'!$B$6-'SUPUESTOS PRECIOS'!$B$7)/'SUPUESTOS PRECIOS'!$B$4 -> 377.5 | W73: ='SUPUESTOS PRECIOS'!$B$8 -> 0.00968 | X73: ='SUPUESTOS PRECIOS'!$B$2 -> 0.4 | Y73: =IF(OR($B73="",$J73=""),"",ROUND(($J73+$T73+$U73+$V73)/(1-$W73-$X73),-1)) -> 8600 | Z73: =IF($Y73="","",$Y73-$J73-$T73-$U73-$V73-($Y73*$W73)) -> 3439.252 | AA73: =IF($Y73="","",$Z73/$Y73) -> 0.39991302 | AB73: EYE-BARREDOR | AC73: 60 CM
A74: 073 | B74: EYE036 | C74: 🧰 Accesorios y equipamiento | D74: Escobas y escobillones | E74: bethel | F74: Repuesto barredor | H74: 1 unidad | I74: EYE036.jpg | J74: 4000 | K74: 0.3 | L74: =IF(J74="","",J74*(1+K74)) -> 5200 | M74: Activo | O74: Activo | P74: NO | Q74: EYE036 | R74: Repuesto barredor. Presentación: 1 unidad. | S74: Escobas y escobillones. Accesorio resistente y práctico, pensado para facilitar las tareas de limpieza del hogar. | T74: ='SUPUESTOS PRECIOS'!$B$9 -> 0 | U74: ='SUPUESTOS PRECIOS'!$B$5/'SUPUESTOS PRECIOS'!$B$4 -> 1000 | V74: =('SUPUESTOS PRECIOS'!$B$6-'SUPUESTOS PRECIOS'!$B$7)/'SUPUESTOS PRECIOS'!$B$4 -> 377.5 | W74: ='SUPUESTOS PRECIOS'!$B$8 -> 0.00968 | X74: ='SUPUESTOS PRECIOS'!$B$2 -> 0.4 | Y74: =IF(OR($B74="",$J74=""),"",ROUND(($J74+$T74+$U74+$V74)/(1-$W74-$X74),-1)) -> 9110 | Z74: =IF($Y74="","",$Y74-$J74-$T74-$U74-$V74-($Y74*$W74)) -> 3644.3152 | AA74: =IF($Y74="","",$Z74/$Y74) -> 0.4000346 | AB74: EYE-BARREDOR | AC74: 80 CM
A75: 074 | B75: EYE037 | C75: 🧰 Accesorios y equipamiento | D75: Escobas y escobillones | E75: bethel | F75: Repuesto barredor | H75: 1 unidad | I75: EYE037.jpg | J75: 4900 | K75: 0.3 | L75: =IF(J75="","",J75*(1+K75)) -> 6370 | M75: Activo | O75: Activo | P75: NO | Q75: EYE037 | R75: Repuesto barredor. Presentación: 1 unidad. | S75: Escobas y escobillones. Accesorio resistente y práctico, pensado para facilitar las tareas de limpieza del hogar. | T75: ='SUPUESTOS PRECIOS'!$B$9 -> 0 | U75: ='SUPUESTOS PRECIOS'!$B$5/'SUPUESTOS PRECIOS'!$B$4 -> 1000 | V75: =('SUPUESTOS PRECIOS'!$B$6-'SUPUESTOS PRECIOS'!$B$7)/'SUPUESTOS PRECIOS'!$B$4 -> 377.5 | W75: ='SUPUESTOS PRECIOS'!$B$8 -> 0.00968 | X75: ='SUPUESTOS PRECIOS'!$B$2 -> 0.4 | Y75: =IF(OR($B75="",$J75=""),"",ROUND(($J75+$T75+$U75+$V75)/(1-$W75-$X75),-1)) -> 10630 | Z75: =IF($Y75="","",$Y75-$J75-$T75-$U75-$V75-($Y75*$W75)) -> 4249.6016 | AA75: =IF($Y75="","",$Z75/$Y75) -> 0.39977437 | AB75: EYE-BARREDOR | AC75: 100 CM
A76: 075 | B76: EYE038 | C76: 🧰 Accesorios y equipamiento | D76: Escobas y escobillones | E76: bethel | F76: Quita Pelusa Make | H76: 1 unidad | I76: EYE038.jpg | J76: 2200 | K76: 0.3 | L76: =IF(J76="","",J76*(1+K76)) -> 2860 | M76: Activo | O76: Activo | P76: NO | Q76: EYE038 | R76: Quita Pelusa Make. Presentación: 1 unidad. | S76: Escobas y escobillones. Accesorio resistente y práctico, pensado para facilitar las tareas de limpieza del hogar. | T76: ='SUPUESTOS PRECIOS'!$B$9 -> 0 | U76: ='SUPUESTOS PRECIOS'!$B$5/'SUPUESTOS PRECIOS'!$B$4 -> 1000 | V76: =('SUPUESTOS PRECIOS'!$B$6-'SUPUESTOS PRECIOS'!$B$7)/'SUPUESTOS PRECIOS'!$B$4 -> 377.5 | W76: ='SUPUESTOS PRECIOS'!$B$8 -> 0.00968 | X76: ='SUPUESTOS PRECIOS'!$B$2 -> 0.4 | Y76: =IF(OR($B76="",$J76=""),"",ROUND(($J76+$T76+$U76+$V76)/(1-$W76-$X76),-1)) -> 6060 | Z76: =IF($Y76="","",$Y76-$J76-$T76-$U76-$V76-($Y76*$W76)) -> 2423.8392 | AA76: =IF($Y76="","",$Z76/$Y76) -> 0.39997347
A77: 076 | B77: AUT001 | C77: 🚗 Automotor | D77: Bruja | E77: bethel | F77: Limpiador Tipo "Bruja" | H77: 1 unidad | I77: AUT001.jpg | J77: 1900 | K77: 0.3 | L77: =IF(J77="","",J77*(1+K77)) -> 2470 | M77: Activo | O77: Activo | P77: NO | Q77: AUT001 | R77: Limpiador Tipo "Bruja". Presentación: 1 unidad. | S77: Bruja. Cuida y da brillo a las superficies del vehículo, prolongando su buen aspecto. | T77: ='SUPUESTOS PRECIOS'!$B$9 -> 0 | U77: ='SUPUESTOS PRECIOS'!$B$5/'SUPUESTOS PRECIOS'!$B$4 -> 1000 | V77: =('SUPUESTOS PRECIOS'!$B$6-'SUPUESTOS PRECIOS'!$B$7)/'SUPUESTOS PRECIOS'!$B$4 -> 377.5 | W77: ='SUPUESTOS PRECIOS'!$B$8 -> 0.00968 | X77: ='SUPUESTOS PRECIOS'!$B$2 -> 0.4 | Y77: =IF(OR($B77="",$J77=""),"",ROUND(($J77+$T77+$U77+$V77)/(1-$W77-$X77),-1)) -> 5550 | Z77: =IF($Y77="","",$Y77-$J77-$T77-$U77-$V77-($Y77*$W77)) -> 2218.776 | AA77: =IF($Y77="","",$Z77/$Y77) -> 0.39977946
A78: 077 | B78: AUT002 | C78: 🚗 Automotor | D78: Esponja | E78: bethel | F78: Esponja para auto | H78: 1 unidad | I78: AUT002.jpg | J78: 800 | K78: 0.3 | L78: =IF(J78="","",J78*(1+K78)) -> 1040 | M78: Activo | O78: Activo | P78: NO | Q78: AUT002 | R78: Esponja para auto. Presentación: 1 unidad. | S78: Esponja. Cuida y da brillo a las superficies del vehículo, prolongando su buen aspecto. | T78: ='SUPUESTOS PRECIOS'!$B$9 -> 0 | U78: ='SUPUESTOS PRECIOS'!$B$5/'SUPUESTOS PRECIOS'!$B$4 -> 1000 | V78: =('SUPUESTOS PRECIOS'!$B$6-'SUPUESTOS PRECIOS'!$B$7)/'SUPUESTOS PRECIOS'!$B$4 -> 377.5 | W78: ='SUPUESTOS PRECIOS'!$B$8 -> 0.00968 | X78: ='SUPUESTOS PRECIOS'!$B$2 -> 0.4 | Y78: =IF(OR($B78="",$J78=""),"",ROUND(($J78+$T78+$U78+$V78)/(1-$W78-$X78),-1)) -> 3690 | Z78: =IF($Y78="","",$Y78-$J78-$T78-$U78-$V78-($Y78*$W78)) -> 1476.7808 | AA78: =IF($Y78="","",$Z78/$Y78) -> 0.4002116
A79: 078 | B79: AUT003 | C79: 🚗 Automotor | D79: Silicona | E79: bethel | F79: Silicona para auto por litro | H79: 1 unidad | I79: AUT003.jpg | J79: 5000 | K79: 0.3 | L79: =IF(J79="","",J79*(1+K79)) -> 6500 | M79: Activo | O79: Activo | P79: NO | Q79: AUT003 | R79: Silicona para auto por litro. Presentación: 1 unidad. | S79: Silicona. Cuida y da brillo a las superficies del vehículo, prolongando su buen aspecto. | T79: ='SUPUESTOS PRECIOS'!$B$9 -> 0 | U79: ='SUPUESTOS PRECIOS'!$B$5/'SUPUESTOS PRECIOS'!$B$4 -> 1000 | V79: =('SUPUESTOS PRECIOS'!$B$6-'SUPUESTOS PRECIOS'!$B$7)/'SUPUESTOS PRECIOS'!$B$4 -> 377.5 | W79: ='SUPUESTOS PRECIOS'!$B$8 -> 0.00968 | X79: ='SUPUESTOS PRECIOS'!$B$2 -> 0.4 | Y79: =IF(OR($B79="",$J79=""),"",ROUND(($J79+$T79+$U79+$V79)/(1-$W79-$X79),-1)) -> 10800 | Z79: =IF($Y79="","",$Y79-$J79-$T79-$U79-$V79-($Y79*$W79)) -> 4317.956 | AA79: =IF($Y79="","",$Z79/$Y79) -> 0.39981074
A80: 079 | B80: AUT004 | C80: 🚗 Automotor | D80: Silicona en Aerosol | E80: Walker | F80: Silicona en Aerosol | G80: Black | H80: 1 unidad | I80: AUT004.jpg | J80: 4100 | K80: 0.3 | L80: =IF(J80="","",J80*(1+K80)) -> 5330 | M80: Activo | O80: Activo | P80: NO | Q80: AUT004 | R80: Silicona en Aerosol. Presentación: 1 unidad. Marca Walker. Fragancia: Black. | S80: Silicona en Aerosol. Cuida y da brillo a las superficies del vehículo, prolongando su buen aspecto. | T80: ='SUPUESTOS PRECIOS'!$B$9 -> 0 | U80: ='SUPUESTOS PRECIOS'!$B$5/'SUPUESTOS PRECIOS'!$B$4 -> 1000 | V80: =('SUPUESTOS PRECIOS'!$B$6-'SUPUESTOS PRECIOS'!$B$7)/'SUPUESTOS PRECIOS'!$B$4 -> 377.5 | W80: ='SUPUESTOS PRECIOS'!$B$8 -> 0.00968 | X80: ='SUPUESTOS PRECIOS'!$B$2 -> 0.4 | Y80: =IF(OR($B80="",$J80=""),"",ROUND(($J80+$T80+$U80+$V80)/(1-$W80-$X80),-1)) -> 9280 | Z80: =IF($Y80="","",$Y80-$J80-$T80-$U80-$V80-($Y80*$W80)) -> 3712.6696 | AA80: =IF($Y80="","",$Z80/$Y80) -> 0.40007216 | AB80: AUT-SILICONA-AEROSOL | AC80: Black
A81: 080 | B81: AUT005 | C81: 🚗 Automotor | D81: Silicona en Aerosol | E81: Walker | F81: Silicona en Aerosol | G81: Carolina Herrera | H81: 1 unidad | I81: AUT005.jpg | J81: 4100 | K81: 0.3 | L81: =IF(J81="","",J81*(1+K81)) -> 5330 | M81: Activo | O81: Activo | P81: NO | Q81: AUT005 | R81: Silicona en Aerosol. Presentación: 1 unidad. Marca Walker. Fragancia: Carolina Herrera. | S81: Silicona en Aerosol. Cuida y da brillo a las superficies del vehículo, prolongando su buen aspecto. | T81: ='SUPUESTOS PRECIOS'!$B$9 -> 0 | U81: ='SUPUESTOS PRECIOS'!$B$5/'SUPUESTOS PRECIOS'!$B$4 -> 1000 | V81: =('SUPUESTOS PRECIOS'!$B$6-'SUPUESTOS PRECIOS'!$B$7)/'SUPUESTOS PRECIOS'!$B$4 -> 377.5 | W81: ='SUPUESTOS PRECIOS'!$B$8 -> 0.00968 | X81: ='SUPUESTOS PRECIOS'!$B$2 -> 0.4 | Y81: =IF(OR($B81="",$J81=""),"",ROUND(($J81+$T81+$U81+$V81)/(1-$W81-$X81),-1)) -> 9280 | Z81: =IF($Y81="","",$Y81-$J81-$T81-$U81-$V81-($Y81*$W81)) -> 3712.6696 | AA81: =IF($Y81="","",$Z81/$Y81) -> 0.40007216 | AB81: AUT-SILICONA-AEROSOL | AC81: Carolina Herrera
A82: 081 | B82: AUT006 | C82: 🚗 Automotor | D82: Silicona en Aerosol | E82: Walker | F82: Silicona en Aerosol | G82: Frutilla | H82: 1 unidad | I82: AUT006.jpg | J82: 4100 | K82: 0.3 | L82: =IF(J82="","",J82*(1+K82)) -> 5330 | M82: Activo | O82: Activo | P82: NO | Q82: AUT006 | R82: Silicona en Aerosol. Presentación: 1 unidad. Marca Walker. Fragancia: Frutilla. | S82: Silicona en Aerosol. Cuida y da brillo a las superficies del vehículo, prolongando su buen aspecto. | T82: ='SUPUESTOS PRECIOS'!$B$9 -> 0 | U82: ='SUPUESTOS PRECIOS'!$B$5/'SUPUESTOS PRECIOS'!$B$4 -> 1000 | V82: =('SUPUESTOS PRECIOS'!$B$6-'SUPUESTOS PRECIOS'!$B$7)/'SUPUESTOS PRECIOS'!$B$4 -> 377.5 | W82: ='SUPUESTOS PRECIOS'!$B$8 -> 0.00968 | X82: ='SUPUESTOS PRECIOS'!$B$2 -> 0.4 | Y82: =IF(OR($B82="",$J82=""),"",ROUND(($J82+$T82+$U82+$V82)/(1-$W82-$X82),-1)) -> 9280 | Z82: =IF($Y82="","",$Y82-$J82-$T82-$U82-$V82-($Y82*$W82)) -> 3712.6696 | AA82: =IF($Y82="","",$Z82/$Y82) -> 0.40007216 | AB82: AUT-SILICONA-AEROSOL | AC82: Frutilla
A83: 082 | B83: AUT007 | C83: 🚗 Automotor | D83: Silicona en Aerosol | E83: Walker | F83: Silicona en Aerosol | G83: Kenzo | H83: 1 unidad | I83: AUT007.jpg | J83: 4100 | K83: 0.3 | L83: =IF(J83="","",J83*(1+K83)) -> 5330 | M83: Activo | O83: Activo | P83: NO | Q83: AUT007 | R83: Silicona en Aerosol. Presentación: 1 unidad. Marca Walker. Fragancia: Kenzo. | S83: Silicona en Aerosol. Cuida y da brillo a las superficies del vehículo, prolongando su buen aspecto. | T83: ='SUPUESTOS PRECIOS'!$B$9 -> 0 | U83: ='SUPUESTOS PRECIOS'!$B$5/'SUPUESTOS PRECIOS'!$B$4 -> 1000 | V83: =('SUPUESTOS PRECIOS'!$B$6-'SUPUESTOS PRECIOS'!$B$7)/'SUPUESTOS PRECIOS'!$B$4 -> 377.5 | W83: ='SUPUESTOS PRECIOS'!$B$8 -> 0.00968 | X83: ='SUPUESTOS PRECIOS'!$B$2 -> 0.4 | Y83: =IF(OR($B83="",$J83=""),"",ROUND(($J83+$T83+$U83+$V83)/(1-$W83-$X83),-1)) -> 9280 | Z83: =IF($Y83="","",$Y83-$J83-$T83-$U83-$V83-($Y83*$W83)) -> 3712.6696 | AA83: =IF($Y83="","",$Z83/$Y83) -> 0.40007216 | AB83: AUT-SILICONA-AEROSOL | AC83: Kenzo
A84: 083 | B84: AUT008 | C84: 🚗 Automotor | D84: Silicona en Aerosol | E84: Walker | F84: Silicona en Aerosol | G84: Lavanda | H84: 1 unidad | I84: AUT008.jpg | J84: 4100 | K84: 0.3 | L84: =IF(J84="","",J84*(1+K84)) -> 5330 | M84: Activo | O84: Activo | P84: NO | Q84: AUT008 | R84: Silicona en Aerosol. Presentación: 1 unidad. Marca Walker. Fragancia: Lavanda. | S84: Silicona en Aerosol. Cuida y da brillo a las superficies del vehículo, prolongando su buen aspecto. | T84: ='SUPUESTOS PRECIOS'!$B$9 -> 0 | U84: ='SUPUESTOS PRECIOS'!$B$5/'SUPUESTOS PRECIOS'!$B$4 -> 1000 | V84: =('SUPUESTOS PRECIOS'!$B$6-'SUPUESTOS PRECIOS'!$B$7)/'SUPUESTOS PRECIOS'!$B$4 -> 377.5 | W84: ='SUPUESTOS PRECIOS'!$B$8 -> 0.00968 | X84: ='SUPUESTOS PRECIOS'!$B$2 -> 0.4 | Y84: =IF(OR($B84="",$J84=""),"",ROUND(($J84+$T84+$U84+$V84)/(1-$W84-$X84),-1)) -> 9280 | Z84: =IF($Y84="","",$Y84-$J84-$T84-$U84-$V84-($Y84*$W84)) -> 3712.6696 | AA84: =IF($Y84="","",$Z84/$Y84) -> 0.40007216 | AB84: AUT-SILICONA-AEROSOL | AC84: Lavanda
A85: 084 | B85: AUT009 | C85: 🚗 Automotor | D85: Silicona en Aerosol | E85: Walker | F85: Silicona en Aerosol | G85: One Million | H85: 1 unidad | I85: AUT009.jpg | J85: 4100 | K85: 0.3 | L85: =IF(J85="","",J85*(1+K85)) -> 5330 | M85: Activo | O85: Activo | P85: NO | Q85: AUT009 | R85: Silicona en Aerosol. Presentación: 1 unidad. Marca Walker. Fragancia: One Million. | S85: Silicona en Aerosol. Cuida y da brillo a las superficies del vehículo, prolongando su buen aspecto. | T85: ='SUPUESTOS PRECIOS'!$B$9 -> 0 | U85: ='SUPUESTOS PRECIOS'!$B$5/'SUPUESTOS PRECIOS'!$B$4 -> 1000 | V85: =('SUPUESTOS PRECIOS'!$B$6-'SUPUESTOS PRECIOS'!$B$7)/'SUPUESTOS PRECIOS'!$B$4 -> 377.5 | W85: ='SUPUESTOS PRECIOS'!$B$8 -> 0.00968 | X85: ='SUPUESTOS PRECIOS'!$B$2 -> 0.4 | Y85: =IF(OR($B85="",$J85=""),"",ROUND(($J85+$T85+$U85+$V85)/(1-$W85-$X85),-1)) -> 9280 | Z85: =IF($Y85="","",$Y85-$J85-$T85-$U85-$V85-($Y85*$W85)) -> 3712.6696 | AA85: =IF($Y85="","",$Z85/$Y85) -> 0.40007216 | AB85: AUT-SILICONA-AEROSOL | AC85: One Million
A86: 085 | B86: AUT010 | C86: 🚗 Automotor | D86: Silicona en Aerosol | E86: Walker | F86: Silicona en Aerosol | G86: Paco rabanne | H86: 1 unidad | I86: AUT010.jpg | J86: 4100 | K86: 0.3 | L86: =IF(J86="","",J86*(1+K86)) -> 5330 | M86: Activo | O86: Activo | P86: NO | Q86: AUT010 | R86: Silicona en Aerosol. Presentación: 1 unidad. Marca Walker. Fragancia: Paco rabanne. | S86: Silicona en Aerosol. Cuida y da brillo a las superficies del vehículo, prolongando su buen aspecto. | T86: ='SUPUESTOS PRECIOS'!$B$9 -> 0 | U86: ='SUPUESTOS PRECIOS'!$B$5/'SUPUESTOS PRECIOS'!$B$4 -> 1000 | V86: =('SUPUESTOS PRECIOS'!$B$6-'SUPUESTOS PRECIOS'!$B$7)/'SUPUESTOS PRECIOS'!$B$4 -> 377.5 | W86: ='SUPUESTOS PRECIOS'!$B$8 -> 0.00968 | X86: ='SUPUESTOS PRECIOS'!$B$2 -> 0.4 | Y86: =IF(OR($B86="",$J86=""),"",ROUND(($J86+$T86+$U86+$V86)/(1-$W86-$X86),-1)) -> 9280 | Z86: =IF($Y86="","",$Y86-$J86-$T86-$U86-$V86-($Y86*$W86)) -> 3712.6696 | AA86: =IF($Y86="","",$Z86/$Y86) -> 0.40007216 | AB86: AUT-SILICONA-AEROSOL | AC86: Paco rabanne
A87: 086 | B87: AUT011 | C87: 🚗 Automotor | D87: Silicona en Aerosol | E87: Walker | F87: Silicona en Aerosol | G87: Sensual | H87: 1 unidad | I87: AUT011.jpg | J87: 4100 | K87: 0.3 | L87: =IF(J87="","",J87*(1+K87)) -> 5330 | M87: Activo | O87: Activo | P87: NO | Q87: AUT011 | R87: Silicona en Aerosol. Presentación: 1 unidad. Marca Walker. Fragancia: Sensual. | S87: Silicona en Aerosol. Cuida y da brillo a las superficies del vehículo, prolongando su buen aspecto. | T87: ='SUPUESTOS PRECIOS'!$B$9 -> 0 | U87: ='SUPUESTOS PRECIOS'!$B$5/'SUPUESTOS PRECIOS'!$B$4 -> 1000 | V87: =('SUPUESTOS PRECIOS'!$B$6-'SUPUESTOS PRECIOS'!$B$7)/'SUPUESTOS PRECIOS'!$B$4 -> 377.5 | W87: ='SUPUESTOS PRECIOS'!$B$8 -> 0.00968 | X87: ='SUPUESTOS PRECIOS'!$B$2 -> 0.4 | Y87: =IF(OR($B87="",$J87=""),"",ROUND(($J87+$T87+$U87+$V87)/(1-$W87-$X87),-1)) -> 9280 | Z87: =IF($Y87="","",$Y87-$J87-$T87-$U87-$V87-($Y87*$W87)) -> 3712.6696 | AA87: =IF($Y87="","",$Z87/$Y87) -> 0.40007216 | AB87: AUT-SILICONA-AEROSOL | AC87: Sensual
A88: 087 | B88: AUT012 | C88: 🚗 Automotor | D88: Silicona en Aerosol | E88: Walker | F88: Silicona en Aerosol | G88: Vainilla | H88: 1 unidad | I88: AUT012.jpg | J88: 4100 | K88: 0.3 | L88: =IF(J88="","",J88*(1+K88)) -> 5330 | M88: Activo | O88: Activo | P88: NO | Q88: AUT012 | R88: Silicona en Aerosol. Presentación: 1 unidad. Marca Walker. Fragancia: Vainilla. | S88: Silicona en Aerosol. Cuida y da brillo a las superficies del vehículo, prolongando su buen aspecto. | T88: ='SUPUESTOS PRECIOS'!$B$9 -> 0 | U88: ='SUPUESTOS PRECIOS'!$B$5/'SUPUESTOS PRECIOS'!$B$4 -> 1000 | V88: =('SUPUESTOS PRECIOS'!$B$6-'SUPUESTOS PRECIOS'!$B$7)/'SUPUESTOS PRECIOS'!$B$4 -> 377.5 | W88: ='SUPUESTOS PRECIOS'!$B$8 -> 0.00968 | X88: ='SUPUESTOS PRECIOS'!$B$2 -> 0.4 | Y88: =IF(OR($B88="",$J88=""),"",ROUND(($J88+$T88+$U88+$V88)/(1-$W88-$X88),-1)) -> 9280 | Z88: =IF($Y88="","",$Y88-$J88-$T88-$U88-$V88-($Y88*$W88)) -> 3712.6696 | AA88: =IF($Y88="","",$Z88/$Y88) -> 0.40007216 | AB88: AUT-SILICONA-AEROSOL | AC88: Vainilla
A89: 088 | B89: AUT013 | C89: 🚗 Automotor | D89: Shampoo Siliconado | E89: bethel | F89: Shampoo Siliconado por litro | H89: 1 unidad | I89: AUT013.jpg | J89: 3000 | K89: 0.3 | L89: =IF(J89="","",J89*(1+K89)) -> 3900 | M89: Activo | O89: Activo | P89: NO | Q89: AUT013 | R89: Shampoo Siliconado por litro. Presentación: 1 unidad. | S89: Shampoo Siliconado. Cuida y da brillo a las superficies del vehículo, prolongando su buen aspecto. | T89: ='SUPUESTOS PRECIOS'!$B$9 -> 0 | U89: ='SUPUESTOS PRECIOS'!$B$5/'SUPUESTOS PRECIOS'!$B$4 -> 1000 | V89: =('SUPUESTOS PRECIOS'!$B$6-'SUPUESTOS PRECIOS'!$B$7)/'SUPUESTOS PRECIOS'!$B$4 -> 377.5 | W89: ='SUPUESTOS PRECIOS'!$B$8 -> 0.00968 | X89: ='SUPUESTOS PRECIOS'!$B$2 -> 0.4 | Y89: =IF(OR($B89="",$J89=""),"",ROUND(($J89+$T89+$U89+$V89)/(1-$W89-$X89),-1)) -> 7420 | Z89: =IF($Y89="","",$Y89-$J89-$T89-$U89-$V89-($Y89*$W89)) -> 2970.6744 | AA89: =IF($Y89="","",$Z89/$Y89) -> 0.40036043
A90: 089 | B90: AUT014 | C90: 🚗 Automotor | D90: Mini Lata Walker | E90: Walker | F90: Mini Lata Walker para auto | G90: universal | H90: 1 unidad | I90: AUT014.jpg | J90: 4300 | K90: 0.3 | L90: =IF(J90="","",J90*(1+K90)) -> 5590 | M90: Activo | O90: Activo | P90: NO | Q90: AUT014 | R90: Mini Lata Walker para auto. Presentación: 1 unidad. Marca Walker. Fragancia: universal. | S90: Mini Lata Walker. Cuida y da brillo a las superficies del vehículo, prolongando su buen aspecto. | T90: ='SUPUESTOS PRECIOS'!$B$9 -> 0 | U90: ='SUPUESTOS PRECIOS'!$B$5/'SUPUESTOS PRECIOS'!$B$4 -> 1000 | V90: =('SUPUESTOS PRECIOS'!$B$6-'SUPUESTOS PRECIOS'!$B$7)/'SUPUESTOS PRECIOS'!$B$4 -> 377.5 | W90: ='SUPUESTOS PRECIOS'!$B$8 -> 0.00968 | X90: ='SUPUESTOS PRECIOS'!$B$2 -> 0.4 | Y90: =IF(OR($B90="",$J90=""),"",ROUND(($J90+$T90+$U90+$V90)/(1-$W90-$X90),-1)) -> 9620 | Z90: =IF($Y90="","",$Y90-$J90-$T90-$U90-$V90-($Y90*$W90)) -> 3849.3784 | AA90: =IF($Y90="","",$Z90/$Y90) -> 0.40014328
A91: 090 | B91: AUT015 | C91: 🚗 Automotor | D91: Perfume en Lata Walker | E91: Walker | F91: Perfume en Lata Walker | G91: Black | H91: 1 unidad | I91: AUT015.jpg | J91: 6500 | K91: 0.3 | L91: =IF(J91="","",J91*(1+K91)) -> 8450 | M91: Activo | O91: Activo | P91: NO | Q91: AUT015 | R91: Perfume en Lata Walker. Presentación: 1 unidad. Marca Walker. Fragancia: Black. | S91: Perfume en Lata Walker. Cuida y da brillo a las superficies del vehículo, prolongando su buen aspecto. | T91: ='SUPUESTOS PRECIOS'!$B$9 -> 0 | U91: ='SUPUESTOS PRECIOS'!$B$5/'SUPUESTOS PRECIOS'!$B$4 -> 1000 | V91: =('SUPUESTOS PRECIOS'!$B$6-'SUPUESTOS PRECIOS'!$B$7)/'SUPUESTOS PRECIOS'!$B$4 -> 377.5 | W91: ='SUPUESTOS PRECIOS'!$B$8 -> 0.00968 | X91: ='SUPUESTOS PRECIOS'!$B$2 -> 0.4 | Y91: =IF(OR($B91="",$J91=""),"",ROUND(($J91+$T91+$U91+$V91)/(1-$W91-$X91),-1)) -> 13340 | Z91: =IF($Y91="","",$Y91-$J91-$T91-$U91-$V91-($Y91*$W91)) -> 5333.3688 | AA91: =IF($Y91="","",$Z91/$Y91) -> 0.39980276 | AB91: AUT-PERFUME-LATA | AC91: Black
A92: 091 | B92: AUT016 | C92: 🚗 Automotor | D92: Perfume en Lata Walker | E92: Walker | F92: Perfume en Lata Walker | G92: Frutilla | H92: 1 unidad | I92: AUT016.jpg | J92: 6500 | K92: 0.3 | L92: =IF(J92="","",J92*(1+K92)) -> 8450 | M92: Activo | O92: Activo | P92: NO | Q92: AUT016 | R92: Perfume en Lata Walker. Presentación: 1 unidad. Marca Walker. Fragancia: Frutilla. | S92: Perfume en Lata Walker. Cuida y da brillo a las superficies del vehículo, prolongando su buen aspecto. | T92: ='SUPUESTOS PRECIOS'!$B$9 -> 0 | U92: ='SUPUESTOS PRECIOS'!$B$5/'SUPUESTOS PRECIOS'!$B$4 -> 1000 | V92: =('SUPUESTOS PRECIOS'!$B$6-'SUPUESTOS PRECIOS'!$B$7)/'SUPUESTOS PRECIOS'!$B$4 -> 377.5 | W92: ='SUPUESTOS PRECIOS'!$B$8 -> 0.00968 | X92: ='SUPUESTOS PRECIOS'!$B$2 -> 0.4 | Y92: =IF(OR($B92="",$J92=""),"",ROUND(($J92+$T92+$U92+$V92)/(1-$W92-$X92),-1)) -> 13340 | Z92: =IF($Y92="","",$Y92-$J92-$T92-$U92-$V92-($Y92*$W92)) -> 5333.3688 | AA92: =IF($Y92="","",$Z92/$Y92) -> 0.39980276 | AB92: AUT-PERFUME-LATA | AC92: Frutilla
A93: 092 | B93: AUT017 | C93: 🚗 Automotor | D93: Perfume en Lata Walker | E93: Walker | F93: Perfume en Lata Walker | G93: Limon | H93: 1 unidad | I93: AUT017.jpg | J93: 6500 | K93: 0.3 | L93: =IF(J93="","",J93*(1+K93)) -> 8450 | M93: Activo | O93: Activo | P93: NO | Q93: AUT017 | R93: Perfume en Lata Walker. Presentación: 1 unidad. Marca Walker. Fragancia: Limon. | S93: Perfume en Lata Walker. Cuida y da brillo a las superficies del vehículo, prolongando su buen aspecto. | T93: ='SUPUESTOS PRECIOS'!$B$9 -> 0 | U93: ='SUPUESTOS PRECIOS'!$B$5/'SUPUESTOS PRECIOS'!$B$4 -> 1000 | V93: =('SUPUESTOS PRECIOS'!$B$6-'SUPUESTOS PRECIOS'!$B$7)/'SUPUESTOS PRECIOS'!$B$4 -> 377.5 | W93: ='SUPUESTOS PRECIOS'!$B$8 -> 0.00968 | X93: ='SUPUESTOS PRECIOS'!$B$2 -> 0.4 | Y93: =IF(OR($B93="",$J93=""),"",ROUND(($J93+$T93+$U93+$V93)/(1-$W93-$X93),-1)) -> 13340 | Z93: =IF($Y93="","",$Y93-$J93-$T93-$U93-$V93-($Y93*$W93)) -> 5333.3688 | AA93: =IF($Y93="","",$Z93/$Y93) -> 0.39980276 | AB93: AUT-PERFUME-LATA | AC93: Limon
A94: 093 | B94: AUT018 | C94: 🚗 Automotor | D94: Perfume en Lata Walker | E94: Walker | F94: Perfume en Lata Walker | G94: Vainilla | H94: 1 unidad | I94: AUT018.jpg | J94: 6500 | K94: 0.3 | L94: =IF(J94="","",J94*(1+K94)) -> 8450 | M94: Activo | O94: Activo | P94: NO | Q94: AUT018 | R94: Perfume en Lata Walker. Presentación: 1 unidad. Marca Walker. Fragancia: Vainilla. | S94: Perfume en Lata Walker. Cuida y da brillo a las superficies del vehículo, prolongando su buen aspecto. | T94: ='SUPUESTOS PRECIOS'!$B$9 -> 0 | U94: ='SUPUESTOS PRECIOS'!$B$5/'SUPUESTOS PRECIOS'!$B$4 -> 1000 | V94: =('SUPUESTOS PRECIOS'!$B$6-'SUPUESTOS PRECIOS'!$B$7)/'SUPUESTOS PRECIOS'!$B$4 -> 377.5 | W94: ='SUPUESTOS PRECIOS'!$B$8 -> 0.00968 | X94: ='SUPUESTOS PRECIOS'!$B$2 -> 0.4 | Y94: =IF(OR($B94="",$J94=""),"",ROUND(($J94+$T94+$U94+$V94)/(1-$W94-$X94),-1)) -> 13340 | Z94: =IF($Y94="","",$Y94-$J94-$T94-$U94-$V94-($Y94*$W94)) -> 5333.3688 | AA94: =IF($Y94="","",$Z94/$Y94) -> 0.39980276 | AB94: AUT-PERFUME-LATA | AC94: Vainilla
A95: 094 | B95: AUT019 | C95: 🚗 Automotor | D95: Perfume en Lata Walker | E95: Walker | F95: Perfume en Lata Walker | G95: Aqua | H95: 1 unidad | I95: AUT019.jpg | J95: 6500 | K95: 0.3 | L95: =IF(J95="","",J95*(1+K95)) -> 8450 | M95: Activo | O95: Activo | P95: NO | Q95: AUT019 | R95: Perfume en Lata Walker. Presentación: 1 unidad. Marca Walker. Fragancia: Aqua. | S95: Perfume en Lata Walker. Cuida y da brillo a las superficies del vehículo, prolongando su buen aspecto. | T95: ='SUPUESTOS PRECIOS'!$B$9 -> 0 | U95: ='SUPUESTOS PRECIOS'!$B$5/'SUPUESTOS PRECIOS'!$B$4 -> 1000 | V95: =('SUPUESTOS PRECIOS'!$B$6-'SUPUESTOS PRECIOS'!$B$7)/'SUPUESTOS PRECIOS'!$B$4 -> 377.5 | W95: ='SUPUESTOS PRECIOS'!$B$8 -> 0.00968 | X95: ='SUPUESTOS PRECIOS'!$B$2 -> 0.4 | Y95: =IF(OR($B95="",$J95=""),"",ROUND(($J95+$T95+$U95+$V95)/(1-$W95-$X95),-1)) -> 13340 | Z95: =IF($Y95="","",$Y95-$J95-$T95-$U95-$V95-($Y95*$W95)) -> 5333.3688 | AA95: =IF($Y95="","",$Z95/$Y95) -> 0.39980276 | AB95: AUT-PERFUME-LATA | AC95: Aqua
A96: 095 | B96: AUT020 | C96: 🚗 Automotor | D96: Cera | E96: bethel | F96: Cera para auto por litro | H96: 1 unidad | I96: AUT020.jpg | J96: 2500 | K96: 0.3 | L96: =IF(J96="","",J96*(1+K96)) -> 3250 | M96: Activo | O96: Activo | P96: NO | Q96: AUT020 | R96: Cera para auto por litro. Presentación: 1 unidad. | S96: Cera. Cuida y da brillo a las superficies del vehículo, prolongando su buen aspecto. | T96: ='SUPUESTOS PRECIOS'!$B$9 -> 0 | U96: ='SUPUESTOS PRECIOS'!$B$5/'SUPUESTOS PRECIOS'!$B$4 -> 1000 | V96: =('SUPUESTOS PRECIOS'!$B$6-'SUPUESTOS PRECIOS'!$B$7)/'SUPUESTOS PRECIOS'!$B$4 -> 377.5 | W96: ='SUPUESTOS PRECIOS'!$B$8 -> 0.00968 | X96: ='SUPUESTOS PRECIOS'!$B$2 -> 0.4 | Y96: =IF(OR($B96="",$J96=""),"",ROUND(($J96+$T96+$U96+$V96)/(1-$W96-$X96),-1)) -> 6570 | Z96: =IF($Y96="","",$Y96-$J96-$T96-$U96-$V96-($Y96*$W96)) -> 2628.9024 | AA96: =IF($Y96="","",$Z96/$Y96) -> 0.40013735
A97: 096 | B97: AUT021 | C97: 🚗 Automotor | D97: Limpia Tapizado en Aerosol | E97: Walker | F97: Limpia Tapizado en Aerosol | H97: 1 unidad | I97: AUT021.jpg | J97: 3400 | K97: 0.3 | L97: =IF(J97="","",J97*(1+K97)) -> 4420 | M97: Activo | O97: Activo | P97: NO | Q97: AUT021 | R97: Limpia Tapizado en Aerosol. Presentación: 1 unidad. Marca Walker. | S97: Limpia Tapizado en Aerosol. Cuida y da brillo a las superficies del vehículo, prolongando su buen aspecto. | T97: ='SUPUESTOS PRECIOS'!$B$9 -> 0 | U97: ='SUPUESTOS PRECIOS'!$B$5/'SUPUESTOS PRECIOS'!$B$4 -> 1000 | V97: =('SUPUESTOS PRECIOS'!$B$6-'SUPUESTOS PRECIOS'!$B$7)/'SUPUESTOS PRECIOS'!$B$4 -> 377.5 | W97: ='SUPUESTOS PRECIOS'!$B$8 -> 0.00968 | X97: ='SUPUESTOS PRECIOS'!$B$2 -> 0.4 | Y97: =IF(OR($B97="",$J97=""),"",ROUND(($J97+$T97+$U97+$V97)/(1-$W97-$X97),-1)) -> 8090 | Z97: =IF($Y97="","",$Y97-$J97-$T97-$U97-$V97-($Y97*$W97)) -> 3234.1888 | AA97: =IF($Y97="","",$Z97/$Y97) -> 0.39977612
A98: 097 | B98: SHA001 | C98: 🚽 Baño | D98: Jabón líquido de manos | E98: bethel | F98: Shampoo para manos | G98: Frutilla | H98: 1 unidad | I98: SHA001.png | J98: 4300 | K98: 0.3 | L98: =IF(J98="","",J98*(1+K98)) -> 5590 | M98: Activo | O98: Activo | P98: NO | Q98: SHA001 | R98: Shampoo para manos. Presentación: 1 unidad. Fragancia: Frutilla. | S98: Jabón líquido de manos. Elimina suciedad y gérmenes en inodoros, azulejos y superficies del baño, dejando un aroma agradable. | T98: ='SUPUESTOS PRECIOS'!$B$9 -> 0 | U98: ='SUPUESTOS PRECIOS'!$B$5/'SUPUESTOS PRECIOS'!$B$4 -> 1000 | V98: =('SUPUESTOS PRECIOS'!$B$6-'SUPUESTOS PRECIOS'!$B$7)/'SUPUESTOS PRECIOS'!$B$4 -> 377.5 | W98: ='SUPUESTOS PRECIOS'!$B$8 -> 0.00968 | X98: ='SUPUESTOS PRECIOS'!$B$2 -> 0.4 | Y98: =IF(OR($B98="",$J98=""),"",ROUND(($J98+$T98+$U98+$V98)/(1-$W98-$X98),-1)) -> 9620 | Z98: =IF($Y98="","",$Y98-$J98-$T98-$U98-$V98-($Y98*$W98)) -> 3849.3784 | AA98: =IF($Y98="","",$Z98/$Y98) -> 0.40014328
A99: 098 | B99: SHA002 | C99: 🚽 Baño | D99: Jabón líquido de manos | E99: bethel | F99: Shampoo para manos por 5 litros | G99: blanco | H99: 1 unidad | I99: SHA002.png | J99: 4300 | K99: 0.3 | L99: =IF(J99="","",J99*(1+K99)) -> 5590 | M99: Activo | O99: Activo | P99: NO | Q99: SHA002 | R99: Shampoo para manos por 5 litros. Presentación: 1 unidad. Fragancia: blanco. | S99: Jabón líquido de manos. Elimina suciedad y gérmenes en inodoros, azulejos y superficies del baño, dejando un aroma agradable. | T99: ='SUPUESTOS PRECIOS'!$B$9 -> 0 | U99: ='SUPUESTOS PRECIOS'!$B$5/'SUPUESTOS PRECIOS'!$B$4 -> 1000 | V99: =('SUPUESTOS PRECIOS'!$B$6-'SUPUESTOS PRECIOS'!$B$7)/'SUPUESTOS PRECIOS'!$B$4 -> 377.5 | W99: ='SUPUESTOS PRECIOS'!$B$8 -> 0.00968 | X99: ='SUPUESTOS PRECIOS'!$B$2 -> 0.4 | Y99: =IF(OR($B99="",$J99=""),"",ROUND(($J99+$T99+$U99+$V99)/(1-$W99-$X99),-1)) -> 9620 | Z99: =IF($Y99="","",$Y99-$J99-$T99-$U99-$V99-($Y99*$W99)) -> 3849.3784 | AA99: =IF($Y99="","",$Z99/$Y99) -> 0.40014328
A100: 099 | B100: SHA003 | C100: 🚽 Baño | D100: Jabón líquido de manos | E100: bethel | F100: Shampoo para manos por 5 litros | G100: vaini coco | H100: 1 unidad | I100: SHA003.png | J100: 4300 | K100: 0.3 | L100: =IF(J100="","",J100*(1+K100)) -> 5590 | M100: Activo | O100: Activo | P100: NO | Q100: SHA003 | R100: Shampoo para manos por 5 litros. Presentación: 1 unidad. Fragancia: vaini coco. | S100: Jabón líquido de manos. Elimina suciedad y gérmenes en inodoros, azulejos y superficies del baño, dejando un aroma agradable. | T100: ='SUPUESTOS PRECIOS'!$B$9 -> 0 | U100: ='SUPUESTOS PRECIOS'!$B$5/'SUPUESTOS PRECIOS'!$B$4 -> 1000 | V100: =('SUPUESTOS PRECIOS'!$B$6-'SUPUESTOS PRECIOS'!$B$7)/'SUPUESTOS PRECIOS'!$B$4 -> 377.5 | W100: ='SUPUESTOS PRECIOS'!$B$8 -> 0.00968 | X100: ='SUPUESTOS PRECIOS'!$B$2 -> 0.4 | Y100: =IF(OR($B100="",$J100=""),"",ROUND(($J100+$T100+$U100+$V100)/(1-$W100-$X100),-1)) -> 9620 | Z100: =IF($Y100="","",$Y100-$J100-$T100-$U100-$V100-($Y100*$W100)) -> 3849.3784 | AA100: =IF($Y100="","",$Z100/$Y100) -> 0.40014328
A101: 100 | B101: SHA004 | C101: 🚽 Baño | D101: Jabón líquido de manos | E101: bethel | F101: Shampoo para manos por 5 litros | G101: manzana | H101: 1 unidad | I101: SHA004.png | J101: 4300 | K101: 0.3 | L101: =IF(J101="","",J101*(1+K101)) -> 5590 | M101: Activo | O101: Activo | P101: NO | Q101: SHA004 | R101: Shampoo para manos por 5 litros. Presentación: 1 unidad. Fragancia: manzana. | S101: Jabón líquido de manos. Elimina suciedad y gérmenes en inodoros, azulejos y superficies del baño, dejando un aroma agradable. | T101: ='SUPUESTOS PRECIOS'!$B$9 -> 0 | U101: ='SUPUESTOS PRECIOS'!$B$5/'SUPUESTOS PRECIOS'!$B$4 -> 1000 | V101: =('SUPUESTOS PRECIOS'!$B$6-'SUPUESTOS PRECIOS'!$B$7)/'SUPUESTOS PRECIOS'!$B$4 -> 377.5 | W101: ='SUPUESTOS PRECIOS'!$B$8 -> 0.00968 | X101: ='SUPUESTOS PRECIOS'!$B$2 -> 0.4 | Y101: =IF(OR($B101="",$J101=""),"",ROUND(($J101+$T101+$U101+$V101)/(1-$W101-$X101),-1)) -> 9620 | Z101: =IF($Y101="","",$Y101-$J101-$T101-$U101-$V101-($Y101*$W101)) -> 3849.3784 | AA101: =IF($Y101="","",$Z101/$Y101) -> 0.40014328
A102: 101 | B102: SHA005 | C102: 🚽 Baño | D102: Jabón líquido de manos | E102: bethel | F102: Shampoo para manos por 5 litros | G102: uva | H102: 1 unidad | I102: SHA005.png | J102: 4300 | K102: 0.3 | L102: =IF(J102="","",J102*(1+K102)) -> 5590 | M102: Activo | O102: Activo | P102: NO | Q102: SHA005 | R102: Shampoo para manos por 5 litros. Presentación: 1 unidad. Fragancia: uva. | S102: Jabón líquido de manos. Elimina suciedad y gérmenes en inodoros, azulejos y superficies del baño, dejando un aroma agradable. | T102: ='SUPUESTOS PRECIOS'!$B$9 -> 0 | U102: ='SUPUESTOS PRECIOS'!$B$5/'SUPUESTOS PRECIOS'!$B$4 -> 1000 | V102: =('SUPUESTOS PRECIOS'!$B$6-'SUPUESTOS PRECIOS'!$B$7)/'SUPUESTOS PRECIOS'!$B$4 -> 377.5 | W102: ='SUPUESTOS PRECIOS'!$B$8 -> 0.00968 | X102: ='SUPUESTOS PRECIOS'!$B$2 -> 0.4 | Y102: =IF(OR($B102="",$J102=""),"",ROUND(($J102+$T102+$U102+$V102)/(1-$W102-$X102),-1)) -> 9620 | Z102: =IF($Y102="","",$Y102-$J102-$T102-$U102-$V102-($Y102*$W102)) -> 3849.3784 | AA102: =IF($Y102="","",$Z102/$Y102) -> 0.40014328
A103: 102 | B103: SHA006 | C103: 🚽 Baño | D103: Jabón líquido de manos | E103: bethel | F103: Shampoo para manos por 5 litros | G103: antibacterial | H103: 1 unidad | I103: SHA006.png | J103: 4300 | K103: 0.3 | L103: =IF(J103="","",J103*(1+K103)) -> 5590 | M103: Activo | O103: Activo | P103: NO | Q103: SHA006 | R103: Shampoo para manos por 5 litros. Presentación: 1 unidad. Fragancia: antibacterial. | S103: Jabón líquido de manos. Elimina suciedad y gérmenes en inodoros, azulejos y superficies del baño, dejando un aroma agradable. | T103: ='SUPUESTOS PRECIOS'!$B$9 -> 0 | U103: ='SUPUESTOS PRECIOS'!$B$5/'SUPUESTOS PRECIOS'!$B$4 -> 1000 | V103: =('SUPUESTOS PRECIOS'!$B$6-'SUPUESTOS PRECIOS'!$B$7)/'SUPUESTOS PRECIOS'!$B$4 -> 377.5 | W103: ='SUPUESTOS PRECIOS'!$B$8 -> 0.00968 | X103: ='SUPUESTOS PRECIOS'!$B$2 -> 0.4 | Y103: =IF(OR($B103="",$J103=""),"",ROUND(($J103+$T103+$U103+$V103)/(1-$W103-$X103),-1)) -> 9620 | Z103: =IF($Y103="","",$Y103-$J103-$T103-$U103-$V103-($Y103*$W103)) -> 3849.3784 | AA103: =IF($Y103="","",$Z103/$Y103) -> 0.40014328
A104: 103 | B104: DAV001 | C104: 🌸 Aromas y fragancias | D104: Difusores aromáticos | E104: Saphirus | F104: Difusor Aromatico Saphirus por 50 CC | G104: vainilla | H104: 1 unidad | I104: DAV001.jpg | J104: 1600 | K104: 0.3 | L104: =IF(J104="","",J104*(1+K104)) -> 2080 | M104: Activo | O104: Activo | P104: NO | Q104: DAV001 | R104: Difusor Aromatico Saphirus por 50 CC. Presentación: 1 unidad. Marca Saphirus. Fragancia: vainilla. | S104: Difusores aromáticos. Perfuma ambientes y textiles con una fragancia agradable y duradera, ideal para dejar todo con olor a limpio. | T104: ='SUPUESTOS PRECIOS'!$B$9 -> 0 | U104: ='SUPUESTOS PRECIOS'!$B$5/'SUPUESTOS PRECIOS'!$B$4 -> 1000 | V104: =('SUPUESTOS PRECIOS'!$B$6-'SUPUESTOS PRECIOS'!$B$7)/'SUPUESTOS PRECIOS'!$B$4 -> 377.5 | W104: ='SUPUESTOS PRECIOS'!$B$8 -> 0.00968 | X104: ='SUPUESTOS PRECIOS'!$B$2 -> 0.4 | Y104: =IF(OR($B104="",$J104=""),"",ROUND(($J104+$T104+$U104+$V104)/(1-$W104-$X104),-1)) -> 5040 | Z104: =IF($Y104="","",$Y104-$J104-$T104-$U104-$V104-($Y104*$W104)) -> 2013.7128 | AA104: =IF($Y104="","",$Z104/$Y104) -> 0.39954619 | AB104: DAV-SIMPLE-DIFUSOR-SAPHIRUS | AC104: vainilla
A105: 104 | B105: DAV002 | C105: 🌸 Aromas y fragancias | D105: Difusores aromáticos | E105: Saphirus | F105: Difusor Aromatico Saphirus por 50 CC | G105: lavanda | H105: 1 unidad | I105: DAV002.jpg | J105: 1600 | K105: 0.3 | L105: =IF(J105="","",J105*(1+K105)) -> 2080 | M105: Activo | O105: Activo | P105: NO | Q105: DAV002 | R105: Difusor Aromatico Saphirus por 50 CC. Presentación: 1 unidad. Marca Saphirus. Fragancia: lavanda. | S105: Difusores aromáticos. Perfuma ambientes y textiles con una fragancia agradable y duradera, ideal para dejar todo con olor a limpio. | T105: ='SUPUESTOS PRECIOS'!$B$9 -> 0 | U105: ='SUPUESTOS PRECIOS'!$B$5/'SUPUESTOS PRECIOS'!$B$4 -> 1000 | V105: =('SUPUESTOS PRECIOS'!$B$6-'SUPUESTOS PRECIOS'!$B$7)/'SUPUESTOS PRECIOS'!$B$4 -> 377.5 | W105: ='SUPUESTOS PRECIOS'!$B$8 -> 0.00968 | X105: ='SUPUESTOS PRECIOS'!$B$2 -> 0.4 | Y105: =IF(OR($B105="",$J105=""),"",ROUND(($J105+$T105+$U105+$V105)/(1-$W105-$X105),-1)) -> 5040 | Z105: =IF($Y105="","",$Y105-$J105-$T105-$U105-$V105-($Y105*$W105)) -> 2013.7128 | AA105: =IF($Y105="","",$Z105/$Y105) -> 0.39954619 | AB105: DAV-SIMPLE-DIFUSOR-SAPHIRUS | AC105: lavanda
A106: 105 | B106: DAV003 | C106: 🌸 Aromas y fragancias | D106: Difusores aromáticos | E106: Saphirus | F106: Difusor Aromatico Saphirus por 50 CC | G106: uva | H106: 1 unidad | I106: DAV003.jpg | J106: 1600 | K106: 0.3 | L106: =IF(J106="","",J106*(1+K106)) -> 2080 | M106: Activo | O106: Activo | P106: NO | Q106: DAV003 | R106: Difusor Aromatico Saphirus por 50 CC. Presentación: 1 unidad. Marca Saphirus. Fragancia: uva. | S106: Difusores aromáticos. Perfuma ambientes y textiles con una fragancia agradable y duradera, ideal para dejar todo con olor a limpio. | T106: ='SUPUESTOS PRECIOS'!$B$9 -> 0 | U106: ='SUPUESTOS PRECIOS'!$B$5/'SUPUESTOS PRECIOS'!$B$4 -> 1000 | V106: =('SUPUESTOS PRECIOS'!$B$6-'SUPUESTOS PRECIOS'!$B$7)/'SUPUESTOS PRECIOS'!$B$4 -> 377.5 | W106: ='SUPUESTOS PRECIOS'!$B$8 -> 0.00968 | X106: ='SUPUESTOS PRECIOS'!$B$2 -> 0.4 | Y106: =IF(OR($B106="",$J106=""),"",ROUND(($J106+$T106+$U106+$V106)/(1-$W106-$X106),-1)) -> 5040 | Z106: =IF($Y106="","",$Y106-$J106-$T106-$U106-$V106-($Y106*$W106)) -> 2013.7128 | AA106: =IF($Y106="","",$Z106/$Y106) -> 0.39954619 | AB106: DAV-SIMPLE-DIFUSOR-SAPHIRUS | AC106: uva
A107: 106 | B107: DAV004 | C107: 🌸 Aromas y fragancias | D107: Difusores aromáticos | E107: Saphirus | F107: Difusor Aromatico Saphirus por 50 CC | G107: palito de la selva | H107: 1 unidad | I107: DAV004.jpg | J107: 1600 | K107: 0.3 | L107: =IF(J107="","",J107*(1+K107)) -> 2080 | M107: Activo | O107: Activo | P107: NO | Q107: DAV004 | R107: Difusor Aromatico Saphirus por 50 CC. Presentación: 1 unidad. Marca Saphirus. Fragancia: palito de la selva. | S107: Difusores aromáticos. Perfuma ambientes y textiles con una fragancia agradable y duradera, ideal para dejar todo con olor a limpio. | T107: ='SUPUESTOS PRECIOS'!$B$9 -> 0 | U107: ='SUPUESTOS PRECIOS'!$B$5/'SUPUESTOS PRECIOS'!$B$4 -> 1000 | V107: =('SUPUESTOS PRECIOS'!$B$6-'SUPUESTOS PRECIOS'!$B$7)/'SUPUESTOS PRECIOS'!$B$4 -> 377.5 | W107: ='SUPUESTOS PRECIOS'!$B$8 -> 0.00968 | X107: ='SUPUESTOS PRECIOS'!$B$2 -> 0.4 | Y107: =IF(OR($B107="",$J107=""),"",ROUND(($J107+$T107+$U107+$V107)/(1-$W107-$X107),-1)) -> 5040 | Z107: =IF($Y107="","",$Y107-$J107-$T107-$U107-$V107-($Y107*$W107)) -> 2013.7128 | AA107: =IF($Y107="","",$Z107/$Y107) -> 0.39954619 | AB107: DAV-SIMPLE-DIFUSOR-SAPHIRUS | AC107: palito de la selva
A108: 107 | B108: DAV005 | C108: 🌸 Aromas y fragancias | D108: Difusores aromáticos | E108: Saphirus | F108: Difusor Aromatico Saphirus por 50 CC | G108: vaini coco | H108: 1 unidad | I108: DAV005.jpg | J108: 1600 | K108: 0.3 | L108: =IF(J108="","",J108*(1+K108)) -> 2080 | M108: Activo | O108: Activo | P108: NO | Q108: DAV005 | R108: Difusor Aromatico Saphirus por 50 CC. Presentación: 1 unidad. Marca Saphirus. Fragancia: vaini coco. | S108: Difusores aromáticos. Perfuma ambientes y textiles con una fragancia agradable y duradera, ideal para dejar todo con olor a limpio. | T108: ='SUPUESTOS PRECIOS'!$B$9 -> 0 | U108: ='SUPUESTOS PRECIOS'!$B$5/'SUPUESTOS PRECIOS'!$B$4 -> 1000 | V108: =('SUPUESTOS PRECIOS'!$B$6-'SUPUESTOS PRECIOS'!$B$7)/'SUPUESTOS PRECIOS'!$B$4 -> 377.5 | W108: ='SUPUESTOS PRECIOS'!$B$8 -> 0.00968 | X108: ='SUPUESTOS PRECIOS'!$B$2 -> 0.4 | Y108: =IF(OR($B108="",$J108=""),"",ROUND(($J108+$T108+$U108+$V108)/(1-$W108-$X108),-1)) -> 5040 | Z108: =IF($Y108="","",$Y108-$J108-$T108-$U108-$V108-($Y108*$W108)) -> 2013.7128 | AA108: =IF($Y108="","",$Z108/$Y108) -> 0.39954619 | AB108: DAV-SIMPLE-DIFUSOR-SAPHIRUS | AC108: vaini coco
A109: 108 | B109: DAV006 | C109: 🌸 Aromas y fragancias | D109: Difusores aromáticos | E109: Saphirus | F109: Difusor Aromatico Saphirus por 50 CC | G109: coniglio | H109: 1 unidad | I109: DAV006.jpg | J109: 1600 | K109: 0.3 | L109: =IF(J109="","",J109*(1+K109)) -> 2080 | M109: Activo | O109: Activo | P109: NO | Q109: DAV006 | R109: Difusor Aromatico Saphirus por 50 CC. Presentación: 1 unidad. Marca Saphirus. Fragancia: coniglio. | S109: Difusores aromáticos. Perfuma ambientes y textiles con una fragancia agradable y duradera, ideal para dejar todo con olor a limpio. | T109: ='SUPUESTOS PRECIOS'!$B$9 -> 0 | U109: ='SUPUESTOS PRECIOS'!$B$5/'SUPUESTOS PRECIOS'!$B$4 -> 1000 | V109: =('SUPUESTOS PRECIOS'!$B$6-'SUPUESTOS PRECIOS'!$B$7)/'SUPUESTOS PRECIOS'!$B$4 -> 377.5 | W109: ='SUPUESTOS PRECIOS'!$B$8 -> 0.00968 | X109: ='SUPUESTOS PRECIOS'!$B$2 -> 0.4 | Y109: =IF(OR($B109="",$J109=""),"",ROUND(($J109+$T109+$U109+$V109)/(1-$W109-$X109),-1)) -> 5040 | Z109: =IF($Y109="","",$Y109-$J109-$T109-$U109-$V109-($Y109*$W109)) -> 2013.7128 | AA109: =IF($Y109="","",$Z109/$Y109) -> 0.39954619 | AB109: DAV-SIMPLE-DIFUSOR-SAPHIRUS | AC109: coniglio
A110: 109 | B110: DAV007 | C110: 🌸 Aromas y fragancias | D110: Difusores aromáticos | E110: Saphirus | F110: Difusor Aromatico Saphirus por 50 CC | G110: limon | H110: 1 unidad | I110: DAV007.jpg | J110: 1600 | K110: 0.3 | L110: =IF(J110="","",J110*(1+K110)) -> 2080 | M110: Activo | O110: Activo | P110: NO | Q110: DAV007 | R110: Difusor Aromatico Saphirus por 50 CC. Presentación: 1 unidad. Marca Saphirus. Fragancia: limon. | S110: Difusores aromáticos. Perfuma ambientes y textiles con una fragancia agradable y duradera, ideal para dejar todo con olor a limpio. | T110: ='SUPUESTOS PRECIOS'!$B$9 -> 0 | U110: ='SUPUESTOS PRECIOS'!$B$5/'SUPUESTOS PRECIOS'!$B$4 -> 1000 | V110: =('SUPUESTOS PRECIOS'!$B$6-'SUPUESTOS PRECIOS'!$B$7)/'SUPUESTOS PRECIOS'!$B$4 -> 377.5 | W110: ='SUPUESTOS PRECIOS'!$B$8 -> 0.00968 | X110: ='SUPUESTOS PRECIOS'!$B$2 -> 0.4 | Y110: =IF(OR($B110="",$J110=""),"",ROUND(($J110+$T110+$U110+$V110)/(1-$W110-$X110),-1)) -> 5040 | Z110: =IF($Y110="","",$Y110-$J110-$T110-$U110-$V110-($Y110*$W110)) -> 2013.7128 | AA110: =IF($Y110="","",$Z110/$Y110) -> 0.39954619 | AB110: DAV-SIMPLE-DIFUSOR-SAPHIRUS | AC110: limon
...

Sheet CATEGORIAS
A1: 🍽️ Cocina
A2: 🚽 Baño
A3: 🧹 Pisos y superficies
A4: 👕 Ropa y lavado
A5: 🦠 Desinfección y limpieza
A6: 🌸 Aromas y fragancias
A7: 📦 Packs y ofertas
A8: 🧰 Accesorios y equipamiento
A9: 🏊 Piletas
A10: 🚗 Automotor
A11: 🏠 Hogar y varios

Sheet MOVIMIENTOS_STOCK
A1: FECHA | B1: CODIGO | C1: ENTRADA | D1: SALIDA | E1: OBSERVACION

Sheet DASHBOARD
A1: Indicador | B1: Valor
A2: Total Productos | B2: =COUNTA(PRODUCTOS!A2:A201) -> 200

Sheet MARCAS
A1: Bethel
A2: K2
A3: Genérica

Sheet PRESENTACIONES
A1: 500 ml
A2: 1 L
A3: 2 L
A4: 5 L
A5: 10 L
A6: 20 L
A7: 25 kg

Sheet CONTROL_FOTOS
A1: Control de fotos del catálogo
A2: Cómo usarla: revisá cada imagen y completá DECISIÓN con MANTENER o REEMPLAZAR. Para las urgentes, reemplazá la imagen antes de publicar la campaña.
A4: CÓDIGO | B4: PRODUCTO | C4: ARCHIVO ACTUAL | D4: PRIORIDAD | E4: HALLAZGO | F4: FOTO RECOMENDADA | G4: DECISIÓN | H4: NOTAS
A5: CLO001 | B5: Lavandina al 4% | C5: CLO001.jpg | D5: PENDIENTE | E5: Revisar manualmente: producto correcto, imagen nítida, fondo limpio y sin marcas ajenas. | F5: Si se reemplaza: foto real del producto, fondo blanco o neutro, buena luz y encuadre cuadrado. | G5: PENDIENTE
A6: DET001 | B6: Detergente 30% | C6: DET001.jpg | D6: PENDIENTE | E6: Revisar manualmente: producto correcto, imagen nítida, fondo limpio y sin marcas ajenas. | F6: Si se reemplaza: foto real del producto, fondo blanco o neutro, buena luz y encuadre cuadrado. | G6: PENDIENTE
A7: LVA001 | B7: Detergente Magistral listo para usar | C7: LVA001.jpg | D7: PENDIENTE | E7: Revisar manualmente: producto correcto, imagen nítida, fondo limpio y sin marcas ajenas. | F7: Si se reemplaza: foto real del producto, fondo blanco o neutro, buena luz y encuadre cuadrado. | G7: PENDIENTE
A8: LVA002 | B8: Lava-Vajillas Concentrado | C8: LVA002.jpg | D8: PENDIENTE | E8: Revisar manualmente: producto correcto, imagen nítida, fondo limpio y sin marcas ajenas. | F8: Si se reemplaza: foto real del producto, fondo blanco o neutro, buena luz y encuadre cuadrado. | G8: PENDIENTE
A9: SUA001 | B9: Suavizante Blanco por 5 litros | C9: SUA001.jpg | D9: PENDIENTE | E9: Revisar manualmente: producto correcto, imagen nítida, fondo limpio y sin marcas ajenas. | F9: Si se reemplaza: foto real del producto, fondo blanco o neutro, buena luz y encuadre cuadrado. | G9: PENDIENTE
A10: SUA002 | B10: Suavizante listo para usar | C10: SUA002.jpg | D10: PENDIENTE | E10: Revisar manualmente: producto correcto, imagen nítida, fondo limpio y sin marcas ajenas. | F10: Si se reemplaza: foto real del producto, fondo blanco o neutro, buena luz y encuadre cuadrado. | G10: PENDIENTE
A11: JBP001 | B11: Jabon en polvo | C11: JBP001.jpg | D11: PENDIENTE | E11: Revisar manualmente: producto correcto, imagen nítida, fondo limpio y sin marcas ajenas. | F11: Si se reemplaza: foto real del producto, fondo blanco o neutro, buena luz y encuadre cuadrado. | G11: PENDIENTE
A12: PFA001 | B12: Perfume aromatico de base en agua | C12: PFA001.jpg | D12: PENDIENTE | E12: Revisar manualmente: producto correcto, imagen nítida, fondo limpio y sin marcas ajenas. | F12: Si se reemplaza: foto real del producto, fondo blanco o neutro, buena luz y encuadre cuadrado. | G12: PENDIENTE
A13: PFA002 | B13: Perfume aromatico de base en alcohol | C13: PFA002.jpg | D13: PENDIENTE | E13: Revisar manualmente: producto correcto, imagen nítida, fondo limpio y sin marcas ajenas. | F13: Si se reemplaza: foto real del producto, fondo blanco o neutro, buena luz y encuadre cuadrado. | G13: PENDIENTE
A14: DES001 | B14: Desengrasante industrial | C14: DES001.jpg | D14: PENDIENTE | E14: Revisar manualmente: producto correcto, imagen nítida, fondo limpio y sin marcas ajenas. | F14: Si se reemplaza: foto real del producto, fondo blanco o neutro, buena luz y encuadre cuadrado. | G14: PENDIENTE
A15: DES002 | B15: Desengrasante lavamotor | C15: DES002.jpg | D15: PENDIENTE | E15: Revisar manualmente: producto correcto, imagen nítida, fondo limpio y sin marcas ajenas. | F15: Si se reemplaza: foto real del producto, fondo blanco o neutro, buena luz y encuadre cuadrado. | G15: PENDIENTE
A16: DES003 | B16: Desengrasante multi usos | C16: DES003.jpg | D16: PENDIENTE | E16: Revisar manualmente: producto correcto, imagen nítida, fondo limpio y sin marcas ajenas. | F16: Si se reemplaza: foto real del producto, fondo blanco o neutro, buena luz y encuadre cuadrado. | G16: PENDIENTE
... A237: VAR009 | B237: Insecticida liquido Gorrion x 500 cc | C237: VAR009.jpg | D237: PENDIENTE | E237: Revisar manualmente: producto correcto, imagen nítida, fondo limpio y sin marcas ajenas. | F237: Si se reemplaza: foto real del producto, fondo blanco o neutro, buena luz y encuadre cuadrado. | G237: PENDIENTE

Sheet SUPUESTOS PRECIOS
A1: Supuestos para el precio de venta
A2: Margen bruto objetivo | B2: 0.4 | C2: % | D2: Precio calculado para dejar 40% de margen luego de costos y comisión.
A3: Supuesto | B3: Valor | C3: Unidad | D3: Nota
A4: Productos promedio por pedido | B4: 4 | C4: productos | D4: Punto medio de 2 a 6 productos.
A5: Viático de abastecimiento por pedido | B5: 4000 | C5: $ / pedido | D5: Costo de ir a comprar y llevar los productos.
A6: Costo real de entrega por pedido | B6: 4000 | C6: $ / pedido | D6: Costo del reparto al cliente.
A7: Envío cobrado de referencia | B7: 2490 | C7: $ / pedido | D7: Tramo recomendado para compras de $15.000 a $19.999.
A8: Comisión de cobro QR Mercado Pago | B8: 0.00968 | C8: % | D8: 0,8% + IVA. Efectivo o transferencia directa: 0%.
A9: Empaque promedio por producto | B9: 0 | C9: $ / producto | D9: Editable: completalo cuando tengas ese costo.
A11: Fórmula aplicada a PRECIO VENTA AJUSTADO
A12: (Costo del producto + Empaque por producto + Viático prorrateado + Subsidio de envío prorrateado) / (1 - Comisión de cobro - Margen bruto objetivo). La comisión está calculada como porcentaje del precio final. Los importes amarillos son editables; las fórmulas del catálogo se actualizan al abrir Excel.

Sheet TARIFAS ENVÍO
A1: Tarifas de envío a domicilio — referencia operativa
A3: Compra de productos | B3: Envío a cobrar | C3: Costo real de entrega | D3: Subsidio absorbido | E3: Mensaje comercial
A4: $10.000 a $14.999 | B4: 2990 | C4: 4000 | D4: 1010 | E4: Envío a domicilio $2.990
A5: $15.000 a $19.999 | B5: 2490 | C5: 4000 | D5: 1510 | E5: Envío a domicilio $2.490
A6: Desde $20.000 | B6: 1990 | C6: 4000 | D6: 2010 | E6: Envío desde $1.990
A8: Política: se cobra un envío proporcional para atraer pedidos; el negocio absorbe la diferencia entre la tarifa y el costo real. La fórmula de precios usa el subsidio del tramo medio ($2.490 de envío).

Sheet CONTROL PRECIOS
A1: Control de cálculo de precios
A3: Control | B3: Resultado
A4: Productos con costo y precio ajustado | B4: =COUNTIFS(PRODUCTOS!$J$2:$J$1001,">0",PRODUCTOS!$Y$2:$Y$1001,">0") -> 234
A5: Filas con productos cargados | B5: =COUNTIFS(PRODUCTOS!$B$2:$B$1001,"<>",PRODUCTOS!$J$2:$J$1001,">0") -> 234
A6: Margen bruto promedio estimado | B6: =AVERAGEIF(PRODUCTOS!$Y$2:$Y$1001,">0",PRODUCTOS!$AA$2:$AA$1001) -> 0.39997751
A7: Estado | B7: =IF(AND(B4>0,B6>='SUPUESTOS PRECIOS'!$B$2-0.005),"OK","REVISAR") -> OK
